Workbook

Sheet Notes
A1: Source & Modeling Notes
A3: Company | B3: Hawkins Cookers Limited
A4: Reporting periods | B4: FY2021 through FY2026
A5: Scope | B5: Standalone financial statements
A6: Units | B6: Rs. Lakhs, as reported in Hawkins annual reports
A7: Historical data | B7: Hardcoded reported historical figures; no forecasts.
A8: FY2021-FY2022 source | B8: Hawkins Annual Report 2021-22, Balance Sheet p.38, Profit & Loss p.39, Cash Flow p.41.
A9: FY2023-FY2024 source | B9: Hawkins Annual Report 2023-24, Balance Sheet p.50, Profit & Loss p.51, Cash Flow p.53.
A10: FY2025-FY2026 source | B10: Hawkins Annual Report 2025-26, Balance Sheet p.30, Profit & Loss p.31, Cash Flow p.33.
A11: Nil treatment | B11: Explicit NIL figures are represented as numeric 0.00 where required for model usability. Blank cells are not used to fabricate values.
A12: Formatting | B12: M&M Income Statement formatting is used as the visual master: colours, borders/lines, fonts, text hierarchy, spacing and number presentation.
A13: Purpose | B13: Historical financial statement database suitable for ratio analysis, assumptions/drivers and three-statement financial modelling.
A16: DATA SHEETS | B16: Historical annual report data sheets (Do Not Change value) but can add Years and values from new Reports
A17: MODELS | B17: Financial Modeling Sheets (Analysis) - Depended on DATA SHEETS

Sheet One Page Profile
B2: One Page Profile - Hawkins Cookers Limited
C4: ='OPP Data'!C2 -> Hawkins Cookers Limited Inc and formerly known as Pressure Cookers and Appliances Ltd, is an Indian company which manufactures pressure cookers and cookware. The company is based in Mumbai and has three manufacturing plants at Thane, Hoshiarpur and Jaunpur. It manufactures under brand names of Hawkins, Futura, Contura, Hevibase, Big Boy, Miss Mary and Ventura. Hawkins is one of the largest pressure cooker manufacturers in India and exports its products to more than 65 countries.
B5: (Values in Rs. Lakhs)
B6: Key Finacial Metrics | C6: 2022 | D6: 2023 | E6: 2024 | F6: 2025 | G6: 2026 | I6: Share Price - 5 Yr
B8: Total Revenue | C8: =HistoricalFS!D9 -> 95801.19 | D8: =HistoricalFS!E9 -> 100579.5 | E8: =HistoricalFS!F9 -> 102414.97 | F8: =HistoricalFS!G9 -> 111575.66 | G8: =HistoricalFS!H9 -> 125292.73
B9: Revenue Growth YoY | C9: =HistoricalFS!D10 -> 0.2466656 | D9: =HistoricalFS!E10 -> 0.049877355 | E9: =HistoricalFS!F10 -> 0.018248947 | F9: =HistoricalFS!G10 -> 0.089446787 | G9: =HistoricalFS!H10 -> 0.12293963
B10: Gross Profit Margins (%) | C10: =HistoricalFS!D13 -> 0.51024742 | D10: =HistoricalFS!E13 -> 0.50845152 | E10: =HistoricalFS!F13 -> 0.48137055 | F10: =HistoricalFS!G13 -> 0.4810197 | G10: =HistoricalFS!H13 -> 0.49207963
B11: EBITDA Margins (%) | C11: =HistoricalFS!D22 -> 0.12500815 | D11: =HistoricalFS!E22 -> 0.13455396 | E11: =HistoricalFS!F22 -> 0.14665786 | F11: =HistoricalFS!G22 -> 0.1385061 | G11: =HistoricalFS!H22 -> 0.1442723
B12: EBIT Margins (%) | C12: ='Ratio Analysis'!D17 -> 0.11805929 | D12: ='Ratio Analysis'!E17 -> 0.12687884 | E12: ='Ratio Analysis'!F17 -> 0.13817873 | F12: ='Ratio Analysis'!G17 -> 0.12928223 | G12: ='Ratio Analysis'!H17 -> 0.13342083
B13: Net Profit Margins (%) | C13: =HistoricalFS!D40 -> 0.087562795 | D13: =HistoricalFS!E40 -> 0.094231131 | E13: =HistoricalFS!F40 -> 0.10724585 | F13: =HistoricalFS!G40 -> 0.10279366 | G13: =HistoricalFS!H40 -> 0.10470544
B14: Earnings Per Share (in Rs) | C14: =HistoricalFS!D44 -> 158.64057 | D14: =HistoricalFS!E44 -> 179.23698 | E14: =HistoricalFS!F44 -> 207.71491 | F14: =HistoricalFS!G44 -> 216.89999 | G14: =HistoricalFS!H44 -> 248.09548
B15: EPS Growth YoY | C15: =HistoricalFS!D45 -> 0.040310929 | D15: =HistoricalFS!E45 -> 0.12983065 | E15: =HistoricalFS!F45 -> 0.1588842 | F15: =HistoricalFS!G45 -> 0.044219644 | G15: =HistoricalFS!H45 -> 0.14382432
B16: Dividend Per Share (in Rs.) | C16: =HistoricalFS!D47 -> 90.350551 | D16: =HistoricalFS!E47 -> 60.679127 | E16: =HistoricalFS!F47 -> 100.68488 | F16: =HistoricalFS!G47 -> 120.22546 | G16: =HistoricalFS!H47 -> 130.00001
B17: Dividend Growth YoY | C17: =(HistoricalFS!D47/HistoricalFS!C47)-1 -> 0.12624085 | D17: =(HistoricalFS!E47/HistoricalFS!D47)-1 -> -0.32840335 | E17: =(HistoricalFS!F47/HistoricalFS!E47)-1 -> 0.65930001 | F17: =(HistoricalFS!G47/HistoricalFS!F47)-1 -> 0.19407667 | G17: =(HistoricalFS!H47/HistoricalFS!G47)-1 -> 0.081301811
B19: Key Finacial Ratios | C19: 2022 | D19: 2023 | E19: 2024 | F19: 2025 | G19: 2026
B21: Price to Earnings
B22: EV/EBITDA
B23: EV/Revenue
B24: Price to Book Value
B25: Return on Equity (%) | C25: ='Ratio Analysis'!D27 -> 0.39349976 | D25: ='Ratio Analysis'!E27 -> 0.34323361 | E25: ='Ratio Analysis'!F27 -> 0.32936228 | F25: ='Ratio Analysis'!G27 -> 0.29926731 | G25: ='Ratio Analysis'!H27 -> 0.29464235
B26: Return on Capital Employed (%) | C26: ='Ratio Analysis'!D25 -> 0.48056118 | D26: ='Ratio Analysis'!E25 -> 0.44382341 | E26: ='Ratio Analysis'!F25 -> 0.43838235 | F26: ='Ratio Analysis'!G25 -> 0.39493441 | G26: ='Ratio Analysis'!H25 -> 0.38685906

Sheet OPP Data
B2: Dsescription | C2: Hawkins Cookers Limited Inc and formerly known as Pressure Cookers and Appliances Ltd, is an Indian company which manufactures pressure cookers and cookware. The company is based in Mumbai and has three manufacturing plants at Thane, Hoshiarpur and Jaunpur. It manufactures under brand names of Hawkins, Futura, Contura, Hevibase, Big Boy, Miss Mary and Ventura. Hawkins is one of the largest pressure cooker manufacturers in India and exports its products to more than 65 countries.
E3: Date | F3: Adj Close | P3: Date | Q3: Adj Close
E4: 46135 | F4: 7452.9468 | P4: 44446 | Q4: 5762.7075
E5: 46136 | F5: 7357.8223 | P5: 44447 | Q5: 5746.4204
E6: 46139 | F6: 7381.1729 | P6: 44448 | Q6: 5784.2676
E7: 46140 | F7: 7362.6655 | P7: 44452 | Q7: 5809.4688
E8: 46141 | F8: 7357.7139 | P8: 44453 | Q8: 5792.1553
E9: 46142 | F9: 7343.7842 | P9: 44454 | Q9: 5854.083
E10: 46146 | F10: 7293.5693 | P10: 44455 | Q10: 5844.6562
E11: 46147 | F11: 7247.3013 | P11: 44456 | Q11: 5787.7217
E12: 46148 | F12: 7241.395 | P12: 44459 | Q12: 5775.6816
E13: 46149 | F13: 7301.4443 | P13: 44460 | Q13: 5800.3687
E14: 46150 | F14: 7377.7368 | P14: 44461 | Q14: 5773.3008
E15: 46153 | F15: 7230.5664 | P15: 44462 | Q15: 5790.4751
... E100: 46272 | F100: 8254 | P100: 44586 | Q100: 5409.4341
P101: 44588 | Q101: 5491.9888
P102: 44589 | Q102: 5469.915
P103: 44592 | Q103: 5562.4565
P104: 44593 | Q104: 5544.6294
P105: 44594 | Q105: 5456.9409
P106: 44595 | Q106: 5405.9341
P107: 44596 | Q107: 5324.9185
P108: 44599 | Q108: 5299.7646
P109: 44600 | Q109: 5256.8774
P110: 44601 | Q110: 5296.7778
P111: 44602 | Q111: 5276.4775
P112: 44603 | Q112: 5223.6035
... P1238: 46269 | Q1238: 8413.3496

Sheet HistoricalFS
B2: Hawkins Cookers Limited
G4: (Values in Rs. Lakhs)
B6: Historical Financials - Hawkins Cookers Limited
B7: Years | C7: 2021 | D7: =C7+1 -> 2022 | E7: =D7+1 -> 2023 | F7: =E7+1 -> 2024 | G7: =F7+1 -> 2025 | H7: =G7+1 -> 2026
A8: # | B8: Income Statement
B9: Revenue from operations | C9: =IFERROR('Income Statement'!B5,0) -> 76845.94 | D9: =IFERROR('Income Statement'!C5,0) -> 95801.19 | E9: =IFERROR('Income Statement'!D5,0) -> 100579.5 | F9: =IFERROR('Income Statement'!E5,0) -> 102414.97 | G9: =IFERROR('Income Statement'!F5,0) -> 111575.66 | H9: =IFERROR('Income Statement'!G5,0) -> 125292.73
B10: Revenue Growth % | D10: =IFERROR(D9/C9-1,0) -> 0.2466656 | E10: =IFERROR(E9/D9-1,0) -> 0.049877355 | F10: =IFERROR(F9/E9-1,0) -> 0.018248947 | G10: =IFERROR(G9/F9-1,0) -> 0.089446787 | H10: =IFERROR(H9/G9-1,0) -> 0.12293963
B12: Cost of Goods Sold | C12: =IFERROR(SUM('Income Statement'!B9:B11),0) -> 36519.71 | D12: =IFERROR(SUM('Income Statement'!C9:C11),0) -> 48882.31 | E12: =IFERROR(SUM('Income Statement'!D9:D11),0) -> 51139.8 | F12: =IFERROR(SUM('Income Statement'!E9:E11),0) -> 49299.55 | G12: =IFERROR(SUM('Income Statement'!F9:F11),0) -> 53670.09 | H12: =IFERROR(SUM('Income Statement'!G9:G11),0) -> 61654
B13: COGS % Revenue | C13: =C12/C9 -> 0.47523278 | D13: =D12/D9 -> 0.51024742 | E13: =E12/E9 -> 0.50845152 | F13: =F12/F9 -> 0.48137055 | G13: =G12/G9 -> 0.4810197 | H13: =H12/H9 -> 0.49207963
B15: Gross Profit | C15: =IFERROR(C9-C12,0) -> 40326.23 | D15: =IFERROR(D9-D12,0) -> 46918.88 | E15: =IFERROR(E9-E12,0) -> 49439.7 | F15: =IFERROR(F9-F12,0) -> 53115.42 | G15: =IFERROR(G9-G12,0) -> 57905.57 | H15: =IFERROR(H9-H12,0) -> 63638.73
B16: Gross Profit Margin % | C16: =C15/C9 -> 0.52476722 | D16: =D15/D9 -> 0.48975258 | E16: =E15/E9 -> 0.49154848 | F16: =F15/F9 -> 0.51862945 | G16: =G15/G9 -> 0.5189803 | H16: =H15/H9 -> 0.50792037
B18: Selling & General Expenses | C18: =IFERROR(SUM('Income Statement'!B12,'Income Statement'!B15),0) -> 29245.31 | D18: =IFERROR(SUM('Income Statement'!C12,'Income Statement'!C15),0) -> 34942.95 | E18: =IFERROR(SUM('Income Statement'!D12,'Income Statement'!D15),0) -> 35906.33 | F18: =IFERROR(SUM('Income Statement'!E12,'Income Statement'!E15),0) -> 38095.46 | G18: =IFERROR(SUM('Income Statement'!F12,'Income Statement'!F15),0) -> 42451.66 | H18: =IFERROR(SUM('Income Statement'!G12,'Income Statement'!G15),0) -> 45562.46
B19: SG&A % Revenue | C19: =C18/C9 -> 0.38057066 | D19: =D18/D9 -> 0.36474443 | E19: =E18/E9 -> 0.35699452 | F19: =F18/F9 -> 0.3719716 | G19: =G18/G9 -> 0.3804742 | H19: =H18/H9 -> 0.36364807
B21: EBITDA | C21: =IFERROR(C15-C18,0) -> 11080.92 | D21: =IFERROR(D15-D18,0) -> 11975.93 | E21: =IFERROR(E15-E18,0) -> 13533.37 | F21: =IFERROR(F15-F18,0) -> 15019.96 | G21: =IFERROR(G15-G18,0) -> 15453.91 | H21: =IFERROR(H15-H18,0) -> 18076.27
B22: EBITDA Margin | C22: =C21/C9 -> 0.14419656 | D22: =D21/D9 -> 0.12500815 | E22: =E21/E9 -> 0.13455396 | F22: =F21/F9 -> 0.14665786 | G22: =G21/G9 -> 0.1385061 | H22: =H21/H9 -> 0.1442723
B24: Finance costs | C24: =IFERROR('Income Statement'!B13,0) -> 473.48 | D24: =IFERROR('Income Statement'!C13,0) -> 605.71 | E24: =IFERROR('Income Statement'!D13,0) -> 486.31 | F24: =IFERROR('Income Statement'!E13,0) -> 455.02 | G24: =IFERROR('Income Statement'!F13,0) -> 290.31 | H24: =IFERROR('Income Statement'!G13,0) -> 352.88
B25: Finance costs % Revenue | C25: =C24/C9 -> 0.0061614185 | D25: =D24/D9 -> 0.0063225728 | E25: =E24/E9 -> 0.0048350807 | F25: =F24/F9 -> 0.0044429052 | G25: =G24/G9 -> 0.0026019116 | H25: =H24/H9 -> 0.0028164443
B27: Depreciation and Amortization | C27: =IFERROR('Income Statement'!B14,0) -> 533.14 | D27: =IFERROR('Income Statement'!C14,0) -> 665.71 | E27: =IFERROR('Income Statement'!D14,0) -> 771.96 | F27: =IFERROR('Income Statement'!E14,0) -> 868.39 | G27: =IFERROR('Income Statement'!F14,0) -> 1029.16 | H27: =IFERROR('Income Statement'!G14,0) -> 1359.61
B28: D&A % Revenue | C28: =C27/C9 -> 0.0069377771 | D28: =D27/D9 -> 0.0069488698 | E28: =E27/E9 -> 0.0076751227 | F28: =F27/F9 -> 0.0084791315 | G28: =G27/G9 -> 0.0092238755 | H28: =H27/H9 -> 0.010851468
B30: Other Income | C30: =IFERROR('Income Statement'!B6,0) -> 731.98 | D30: =IFERROR('Income Statement'!C6,0) -> 586.12 | E30: =IFERROR('Income Statement'!D6,0) -> 416 | F30: =IFERROR('Income Statement'!E6,0) -> 1058.36 | G30: =IFERROR('Income Statement'!F6,0) -> 1352.86 | H30: =IFERROR('Income Statement'!G6,0) -> 1297.9
B31: Other Income % Revenue | C31: =C30/C9 -> 0.0095252918 | D31: =D30/D9 -> 0.0061180868 | E31: =E30/E9 -> 0.0041360317 | F31: =F30/F9 -> 0.010334036 | G31: =G30/G9 -> 0.012125046 | H31: =H30/H9 -> 0.010358941
B33: Earnings before Tax (EBT) | C33: =C21-SUM(C27,C24)+C30 -> 10806.28 | D33: =D21-SUM(D27,D24)+D30 -> 11290.63 | E33: =E21-SUM(E27,E24)+E30 -> 12691.1 | F33: =F21-SUM(F27,F24)+F30 -> 14754.91 | G33: =G21-SUM(G27,G24)+G30 -> 15487.3 | H33: =H21-SUM(H27,H24)+H30 -> 17661.68
B34: EBT Margins | C34: =C33/C9 -> 0.14062265 | D34: =D33/D9 -> 0.1178548 | E34: =E33/E9 -> 0.12617979 | F34: =F33/F9 -> 0.14406986 | G34: =G33/G9 -> 0.13880536 | H34: =H33/H9 -> 0.14096333
B36: Tax | C36: =IFERROR(SUM('Income Statement'!B19:B20),0) -> 2742.71 | D36: =IFERROR(SUM('Income Statement'!C19:C20),0) -> 2902.01 | E36: =IFERROR(SUM('Income Statement'!D19:D20),0) -> 3213.38 | F36: =IFERROR(SUM('Income Statement'!E19:E20),0) -> 3771.33 | G36: =IFERROR(SUM('Income Statement'!F19:F20),0) -> 4018.03 | H36: =IFERROR(SUM('Income Statement'!G19:G20),0) -> 4542.85
B37: Effective Tax Rate | C37: =C36/C33 -> 0.25380705 | D37: =D36/D33 -> 0.25702817 | E37: =E36/E33 -> 0.25319949 | F37: =F36/F33 -> 0.25559831 | G37: =G36/G33 -> 0.25944032 | H37: =H36/H33 -> 0.25721506
B39: Net Profit | C39: =C33-C36 -> 8063.57 | D39: =D33-D36 -> 8388.62 | E39: =E33-E36 -> 9477.72 | F39: =F33-F36 -> 10983.58 | G39: =G33-G36 -> 11469.27 | H39: =H33-H36 -> 13118.83
B40: Net Margins | C40: =C39/C9 -> 0.10493163 | D40: =D39/D9 -> 0.087562795 | E40: =E39/E9 -> 0.094231131 | F40: =F39/F9 -> 0.10724585 | G40: =G39/G9 -> 0.10279366 | H40: =H39/H9 -> 0.10470544
B42: No. of Equity Shares (in lakhs) | C42: =5287815/100000 -> 52.87815 | D42: =5287815/100000 -> 52.87815 | E42: =5287815/100000 -> 52.87815 | F42: =5287815/100000 -> 52.87815 | G42: =5287815/100000 -> 52.87815 | H42: =5287815/100000 -> 52.87815
B44: Earnings Per Share | C44: =IFERROR(C39/C42,0) -> 152.49342 | D44: =IFERROR(D39/D42,0) -> 158.64057 | E44: =IFERROR(E39/E42,0) -> 179.23698 | F44: =IFERROR(F39/F42,0) -> 207.71491 | G44: =IFERROR(G39/G42,0) -> 216.89999 | H44: =IFERROR(H39/H42,0) -> 248.09548
B45: EPS Growth | D45: =IFERROR(D44/C44-1,0) -> 0.040310929 | E45: =IFERROR(E44/D44-1,0) -> 0.12983065 | F45: =IFERROR(F44/E44-1,0) -> 0.1588842 | G45: =IFERROR(G44/F44-1,0) -> 0.044219644 | H45: =IFERROR(H44/G44-1,0) -> 0.14382432
B47: Dividend Per Share | C47: =IFERROR((('Cash Flow'!B40*-1)/HistoricalFS!C42),0) -> 80.223117 | D47: =IFERROR((('Cash Flow'!C40*-1)/HistoricalFS!D42),0) -> 90.350551 | E47: =IFERROR((('Cash Flow'!D40*-1)/HistoricalFS!E42),0) -> 60.679127 | F47: =IFERROR((('Cash Flow'!E40*-1)/HistoricalFS!F42),0) -> 100.68488 | G47: =IFERROR((('Cash Flow'!F40*-1)/HistoricalFS!G42),0) -> 120.22546 | H47: =IFERROR((('Cash Flow'!G40*-1)/HistoricalFS!H42),0) -> 130.00001
B48: Dividend Payout Ratio | C48: =C47/C44 -> 0.52607592 | D48: =D47/D44 -> 0.56952991 | E48: =E47/E44 -> 0.33854134 | F48: =F47/F44 -> 0.48472629 | G48: =G47/G44 -> 0.55428985 | H48: =H47/H44 -> 0.52399185
B50: Retained Earnings | C50: =IFERROR(1-C48,0) -> 0.47392408 | D50: =IFERROR(1-D48,0) -> 0.43047009 | E50: =IFERROR(1-E48,0) -> 0.66145866 | F50: =IFERROR(1-F48,0) -> 0.51527371 | G50: =IFERROR(1-G48,0) -> 0.44571015 | H50: =IFERROR(1-H48,0) -> 0.47600815
A52: # | B52: Balance Sheet
B53: NON-CURRENT ASSETS
B54: Property, Plant and Equipment | C54: =IFERROR('Balance Sheet'!B7,0) -> 3891.85 | D54: =IFERROR('Balance Sheet'!C7,0) -> 5162.06 | E54: =IFERROR('Balance Sheet'!D7,0) -> 6601.99 | F54: =IFERROR('Balance Sheet'!E7,0) -> 7195.46 | G54: =IFERROR('Balance Sheet'!F7,0) -> 8432.04 | H54: =IFERROR('Balance Sheet'!G7,0) -> 11997.55
B55: Capital Work-in-Progress | C55: =IFERROR('Balance Sheet'!B8,0) -> 277.98 | D55: =IFERROR('Balance Sheet'!C8,0) -> 323.11 | E55: =IFERROR('Balance Sheet'!D8,0) -> 215.95 | F55: =IFERROR('Balance Sheet'!E8,0) -> 1188.22 | G55: =IFERROR('Balance Sheet'!F8,0) -> 2245.13 | H55: =IFERROR('Balance Sheet'!G8,0) -> 1194.98
B56: Intangible assets | C56: =IFERROR('Balance Sheet'!B9,0) -> 9.49 | D56: =IFERROR('Balance Sheet'!C9,0) -> 17.19 | E56: =IFERROR('Balance Sheet'!D9,0) -> 15.28 | F56: =IFERROR('Balance Sheet'!E9,0) -> 11.87 | G56: =IFERROR('Balance Sheet'!F9,0) -> 45.98 | H56: =IFERROR('Balance Sheet'!G9,0) -> 68.94
B57: Investments | C57: =IFERROR('Balance Sheet'!B11,0) -> 0.25 | D57: =IFERROR('Balance Sheet'!C11,0) -> 0.25 | E57: =IFERROR('Balance Sheet'!D11,0) -> 0.25 | F57: =IFERROR('Balance Sheet'!E11,0) -> 0.25 | G57: =IFERROR('Balance Sheet'!F11,0) -> 0.25 | H57: =IFERROR('Balance Sheet'!G11,0) -> 0.25
B58: Other non-current financial assets | C58: =IFERROR('Balance Sheet'!B12,0) -> 1109.62 | D58: =IFERROR('Balance Sheet'!C12,0) -> 130.47 | E58: =IFERROR('Balance Sheet'!D12,0) -> 779.34 | F58: =IFERROR('Balance Sheet'!E12,0) -> 445.84 | G58: =IFERROR('Balance Sheet'!F12,0) -> 936.04 | H58: =IFERROR('Balance Sheet'!G12,0) -> 543.14
B59: Non-current tax assets (net) | C59: =IFERROR('Balance Sheet'!B13,0) -> 208.62 | D59: =IFERROR('Balance Sheet'!C13,0) -> 316.71 | E59: =IFERROR('Balance Sheet'!D13,0) -> 296.08 | F59: =IFERROR('Balance Sheet'!E13,0) -> 315.17 | G59: =IFERROR('Balance Sheet'!F13,0) -> 443.25 | H59: =IFERROR('Balance Sheet'!G13,0) -> 421.74
B60: Deferred tax assets (net) | C60: =IFERROR('Balance Sheet'!B14,0) -> 85.79 | D60: =IFERROR('Balance Sheet'!C14,0) -> 36.3 | E60: =IFERROR('Balance Sheet'!D14,0) -> 113.8 | F60: =IFERROR('Balance Sheet'!E14,0) -> 88.29 | G60: =IFERROR('Balance Sheet'!F14,0) -> 18.97 | H60: =IFERROR('Balance Sheet'!G14,0) -> 0
B61: Other non-current assets | C61: =IFERROR('Balance Sheet'!B15,0) -> 364.97 | D61: =IFERROR('Balance Sheet'!C15,0) -> 521.32 | E61: =IFERROR('Balance Sheet'!D15,0) -> 556.08 | F61: =IFERROR('Balance Sheet'!E15,0) -> 684.15 | G61: =IFERROR('Balance Sheet'!F15,0) -> 625.93 | H61: =IFERROR('Balance Sheet'!G15,0) -> 668.89
B63: CURRENT ASSETS
B64: Inventories | C64: =IFERROR('Balance Sheet'!B18,0) -> 9717.53 | D64: =IFERROR('Balance Sheet'!C18,0) -> 17810.07 | E64: =IFERROR('Balance Sheet'!D18,0) -> 16956.37 | F64: =IFERROR('Balance Sheet'!E18,0) -> 14045.67 | G64: =IFERROR('Balance Sheet'!F18,0) -> 15016.63 | H64: =IFERROR('Balance Sheet'!G18,0) -> 19296.57
B65: Trade receivables | C65: =IFERROR('Balance Sheet'!B20,0) -> 4000.29 | D65: =IFERROR('Balance Sheet'!C20,0) -> 5282.95 | E65: =IFERROR('Balance Sheet'!D20,0) -> 4741.56 | F65: =IFERROR('Balance Sheet'!E20,0) -> 4770.81 | G65: =IFERROR('Balance Sheet'!F20,0) -> 6099.88 | H65: =IFERROR('Balance Sheet'!G20,0) -> 5760.91
B66: Cash and cash equivalents | C66: =IFERROR('Balance Sheet'!B21,0) -> 2133.57 | D66: =IFERROR('Balance Sheet'!C21,0) -> 315.42 | E66: =IFERROR('Balance Sheet'!D21,0) -> 1144.31 | F66: =IFERROR('Balance Sheet'!E21,0) -> 1206.21 | G66: =IFERROR('Balance Sheet'!F21,0) -> 1074.26 | H66: =IFERROR('Balance Sheet'!G21,0) -> 1569.45
B67: Bank balances other than above | C67: =IFERROR('Balance Sheet'!B22,0) -> 14574.68 | D67: =IFERROR('Balance Sheet'!C22,0) -> 6198.47 | E67: =IFERROR('Balance Sheet'!D22,0) -> 8710.34 | F67: =IFERROR('Balance Sheet'!E22,0) -> 17628.87 | G67: =IFERROR('Balance Sheet'!F22,0) -> 17900.06 | H67: =IFERROR('Balance Sheet'!G22,0) -> 17522.66
B68: Other current financial assets | C68: =IFERROR('Balance Sheet'!B23,0) -> 523.47 | D68: =IFERROR('Balance Sheet'!C23,0) -> 242.07 | E68: =IFERROR('Balance Sheet'!D23,0) -> 237.07 | F68: =IFERROR('Balance Sheet'!E23,0) -> 490.93 | G68: =IFERROR('Balance Sheet'!F23,0) -> 592.71 | H68: =IFERROR('Balance Sheet'!G23,0) -> 454.39
B69: Other current assets | C69: =IFERROR('Balance Sheet'!B24,0) -> 2306.33 | D69: =IFERROR('Balance Sheet'!C24,0) -> 4618.89 | E69: =IFERROR('Balance Sheet'!D24,0) -> 5669.81 | F69: =IFERROR('Balance Sheet'!E24,0) -> 4548.34 | G69: =IFERROR('Balance Sheet'!F24,0) -> 4959.61 | H69: =IFERROR('Balance Sheet'!G24,0) -> 9322.46
B71: TOTAL ASSETS | C71: =IFERROR(SUM(C54:C69),0) -> 39204.44 | D71: =IFERROR(SUM(D54:D69),0) -> 40975.28 | E71: =IFERROR(SUM(E54:E69),0) -> 46038.23 | F71: =IFERROR(SUM(F54:F69),0) -> 52620.08 | G71: =IFERROR(SUM(G54:G69),0) -> 58390.74 | H71: =IFERROR(SUM(H54:H69),0) -> 68821.93
B73: EQUITY
B74: Equity Share Capital | C74: =IFERROR('Balance Sheet'!B29,0) -> 528.78 | D74: =IFERROR('Balance Sheet'!C29,0) -> 528.78 | E74: =IFERROR('Balance Sheet'!D29,0) -> 528.78 | F74: =IFERROR('Balance Sheet'!E29,0) -> 528.78 | G74: =IFERROR('Balance Sheet'!F29,0) -> 528.78 | H74: =IFERROR('Balance Sheet'!G29,0) -> 528.78
B75: Other Equity | C75: =IFERROR('Balance Sheet'!B30,0) -> 17233.66 | D75: =IFERROR('Balance Sheet'!C30,0) -> 20789.2 | E75: =IFERROR('Balance Sheet'!D30,0) -> 27084.25 | F75: =IFERROR('Balance Sheet'!E30,0) -> 32819.24 | G75: =IFERROR('Balance Sheet'!F30,0) -> 37795.72 | H75: =IFERROR('Balance Sheet'!G30,0) -> 43995.81
B77: NON-CURRENT LIABILITIES
B78: Borrowings | C78: =IFERROR('Balance Sheet'!B35,0) -> 2305.76 | D78: =IFERROR('Balance Sheet'!C35,0) -> 3437.12 | E78: =IFERROR('Balance Sheet'!D35,0) -> 2077.63 | F78: =IFERROR('Balance Sheet'!E35,0) -> 1347.56 | G78: =IFERROR('Balance Sheet'!F35,0) -> 1625.45 | H78: =IFERROR('Balance Sheet'!G35,0) -> 2041.62
B79: Other non-current financial liabilities | C79: =IFERROR('Balance Sheet'!B36,0) -> 0 | D79: =IFERROR('Balance Sheet'!C36,0) -> 0 | E79: =IFERROR('Balance Sheet'!D36,0) -> 124.97 | F79: =IFERROR('Balance Sheet'!E36,0) -> 51.27 | G79: =IFERROR('Balance Sheet'!F36,0) -> 76.56 | H79: =IFERROR('Balance Sheet'!G36,0) -> 105.26
B80: Provisions | C80: =IFERROR('Balance Sheet'!B37,0) -> 562.07 | D80: =IFERROR('Balance Sheet'!C37,0) -> 618.39 | E80: =IFERROR('Balance Sheet'!D37,0) -> 843.92 | F80: =IFERROR('Balance Sheet'!E37,0) -> 895.69 | G80: =IFERROR('Balance Sheet'!F37,0) -> 830.86 | H80: =IFERROR('Balance Sheet'!G37,0) -> 792.95
B81: Deferred tax liabilities (net) | C81: =IFERROR('Balance Sheet'!B38,0) -> 0 | D81: =IFERROR('Balance Sheet'!C38,0) -> 0 | E81: =IFERROR('Balance Sheet'!D38,0) -> 0 | F81: =IFERROR('Balance Sheet'!E38,0) -> 0 | G81: =IFERROR('Balance Sheet'!F38,0) -> 0 | H81: =IFERROR('Balance Sheet'!G38,0) -> 45.88
B83: CURRENT LIABILITIES
B84: Borrowings | C84: =IFERROR('Balance Sheet'!B42,0) -> 1447.01 | D84: =IFERROR('Balance Sheet'!C42,0) -> 902.71 | E84: =IFERROR('Balance Sheet'!D42,0) -> 2153.52 | F84: =IFERROR('Balance Sheet'!E42,0) -> 1788.33 | G84: =IFERROR('Balance Sheet'!F42,0) -> 687.18 | H84: =IFERROR('Balance Sheet'!G42,0) -> 897.19
B85: Trade payables - To micro & small enterprises | C85: =IFERROR('Balance Sheet'!B43,0) -> 774.79 | D85: =IFERROR('Balance Sheet'!C43,0) -> 2488.83 | E85: =IFERROR('Balance Sheet'!D43,0) -> 1659.36 | F85: =IFERROR('Balance Sheet'!E43,0) -> 2383.9 | G85: =IFERROR('Balance Sheet'!F43,0) -> 3458.73 | H85: =IFERROR('Balance Sheet'!G43,0) -> 3705.41
B86: Trade payables - To other than micro & small enterprises | C86: =IFERROR('Balance Sheet'!B44,0) -> 6880.6 | D86: =IFERROR('Balance Sheet'!C44,0) -> 4722.8 | E86: =IFERROR('Balance Sheet'!D44,0) -> 4388.55 | F86: =IFERROR('Balance Sheet'!E44,0) -> 4488.53 | G86: =IFERROR('Balance Sheet'!F44,0) -> 4450.94 | H86: =IFERROR('Balance Sheet'!G44,0) -> 5939
B87: Other current financial liabilities | C87: =IFERROR('Balance Sheet'!B45,0) -> 4490.58 | D87: =IFERROR('Balance Sheet'!C45,0) -> 4179.39 | E87: =IFERROR('Balance Sheet'!D45,0) -> 3936.55 | F87: =IFERROR('Balance Sheet'!E45,0) -> 4983.14 | G87: =IFERROR('Balance Sheet'!F45,0) -> 5142.97 | H87: =IFERROR('Balance Sheet'!G45,0) -> 5572.98
B88: Other current liabilities | C88: =IFERROR('Balance Sheet'!B46,0) -> 4722.14 | D88: =IFERROR('Balance Sheet'!C46,0) -> 3095.98 | E88: =IFERROR('Balance Sheet'!D46,0) -> 2876.28 | F88: =IFERROR('Balance Sheet'!E46,0) -> 2801 | G88: =IFERROR('Balance Sheet'!F46,0) -> 3439.08 | H88: =IFERROR('Balance Sheet'!G46,0) -> 4549.33
B89: Provisions | C89: =IFERROR('Balance Sheet'!B47,0) -> 133.84 | D89: =IFERROR('Balance Sheet'!C47,0) -> 161.04 | E89: =IFERROR('Balance Sheet'!D47,0) -> 364.41 | F89: =IFERROR('Balance Sheet'!E47,0) -> 329.91 | G89: =IFERROR('Balance Sheet'!F47,0) -> 273.02 | H89: =IFERROR('Balance Sheet'!G47,0) -> 270.47
B90: Current Tax Liabilities (net) | C90: =IFERROR('Balance Sheet'!B48,0) -> 125.21 | D90: =IFERROR('Balance Sheet'!C48,0) -> 51.03 | E90: =IFERROR('Balance Sheet'!D48,0) -> 0 | F90: =IFERROR('Balance Sheet'!E48,0) -> 202.75 | G90: =IFERROR('Balance Sheet'!F48,0) -> 81.45 | H90: =IFERROR('Balance Sheet'!G48,0) -> 377.22
B92: TOTAL EQUITY AND LIABILITIES | C92: =IFERROR(SUM(C74:C90),0) -> 39204.44 | D92: =IFERROR(SUM(D74:D90),0) -> 40975.27 | E92: =IFERROR(SUM(E74:E90),0) -> 46038.22 | F92: =IFERROR(SUM(F74:F90),0) -> 52620.1 | G92: =IFERROR(SUM(G74:G90),0) -> 58390.74 | H92: =IFERROR(SUM(H74:H90),0) -> 68821.9
B94: check | C94: =C92-C71 -> 0 | D94: =D92-D71 -> -0.01 | E94: =E92-E71 -> -0.01 | F94: =F92-F71 -> 0.02 | G94: =G92-G71 -> 0 | H94: =H92-H71 -> -0.03
A96: # | B96: Cash Flow Statement
B97: Operating Activites
B98: Net Cash from/(used) in Operating Activities | C98: =IFERROR('Cash Flow'!B30,0) -> 18893.91 | D98: =IFERROR('Cash Flow'!C30,0) -> -5215.15 | E98: =IFERROR('Cash Flow'!D30,0) -> 9226.51 | F98: =IFERROR('Cash Flow'!E30,0) -> 17425.99 | G98: =IFERROR('Cash Flow'!F30,0) -> 10191.25 | H98: =IFERROR('Cash Flow'!G30,0) -> 8759.34
B100: Investing Activities
B101: Net Cash from/(used) in Investing Activities | C101: =IFERROR('Cash Flow'!B37,0) -> -11938.89 | D101: =IFERROR('Cash Flow'!C37,0) -> 8197.7 | E101: =IFERROR('Cash Flow'!D37,0) -> -4746.87 | F101: =IFERROR('Cash Flow'!E37,0) -> -10355.49 | G101: =IFERROR('Cash Flow'!F37,0) -> -2745.71 | H101: =IFERROR('Cash Flow'!G37,0) -> -1705.39
B103: Financing Activities
B104: Net Cash used in Financing Activities | C104: =IFERROR('Cash Flow'!B43,0) -> -4015.77 | D104: =IFERROR('Cash Flow'!C43,0) -> -5127.96 | E104: =IFERROR('Cash Flow'!D43,0) -> -3324.81 | F104: =IFERROR('Cash Flow'!E43,0) -> -7007.27 | G104: =IFERROR('Cash Flow'!F43,0) -> -7577.48 | H104: =IFERROR('Cash Flow'!G43,0) -> -6558.76
B106: Net Increase/(Decrease) in Cash and Cash Equivalents | C106: =IFERROR('Cash Flow'!B44,0) -> 2939.25 | D106: =IFERROR('Cash Flow'!C44,0) -> -2145.41 | E106: =IFERROR('Cash Flow'!D44,0) -> 1154.83 | F106: =IFERROR('Cash Flow'!E44,0) -> 63.22 | G106: =IFERROR('Cash Flow'!F44,0) -> -131.95 | H106: =IFERROR('Cash Flow'!G44,0) -> 495.19
B108: Cash at beginning of year | C108: =IFERROR('Cash Flow'!B45,0) -> -805.68 | D108: =IFERROR('Cash Flow'!C45,0) -> 2133.57 | E108: =IFERROR('Cash Flow'!D45,0) -> -11.84 | F108: =IFERROR('Cash Flow'!E45,0) -> 1142.99 | G108: =IFERROR('Cash Flow'!F45,0) -> 1206.21 | H108: =IFERROR('Cash Flow'!G45,0) -> 1074.26
B109: Cash at end of year | C109: =IFERROR('Cash Flow'!B46,0) -> 2133.57 | D109: =IFERROR('Cash Flow'!C46,0) -> -11.84 | E109: =IFERROR('Cash Flow'!D46,0) -> 1142.99 | F109: =IFERROR('Cash Flow'!E46,0) -> 1206.21 | G109: =IFERROR('Cash Flow'!F46,0) -> 1074.26 | H109: =IFERROR('Cash Flow'!G46,0) -> 1569.45
B111: check | C111: =C106-SUM(C98:C104) -> 0 | D111: =D106-SUM(D98:D104) -> 0 | E111: =E106-SUM(E98:E104) -> 0 | F111: =F106-SUM(F98:F104) -> -0.01 | G111: =G106-SUM(G98:G104) -> -0.01 | H111: =H106-SUM(H98:H104) -> 0

Sheet Ratio Analysis
B2: Hawkins Cookers Limited
J4: (Values in Rs. Lakhs)
B6: Ratio Analysis - Hawkins Cookers Limited
B7: Years | C7: 2021 | D7: =C7+1 -> 2022 | E7: =D7+1 -> 2023 | F7: =E7+1 -> 2024 | G7: =F7+1 -> 2025 | H7: =G7+1 -> 2026 | I7: Trend | J7: Mean | K7: Median
B9: Revenue Growth | D9: =IFERROR(HistoricalFS!D10,0) -> 0.2466656 | E9: =IFERROR(HistoricalFS!E10,0) -> 0.049877355 | F9: =IFERROR(HistoricalFS!F10,0) -> 0.018248947 | G9: =IFERROR(HistoricalFS!G10,0) -> 0.089446787 | H9: =IFERROR(HistoricalFS!H10,0) -> 0.12293963 | J9: =AVERAGE(D9:H9) -> 0.10543566 | K9: =MEDIAN(D9:H9) -> 0.089446787
B10: EBITDA Growth | D10: =IFERROR((HistoricalFS!D21/HistoricalFS!C21-1),0) -> 0.080770369 | E10: =IFERROR((HistoricalFS!E21/HistoricalFS!D21-1),0) -> 0.13004752 | F10: =IFERROR((HistoricalFS!F21/HistoricalFS!E21-1),0) -> 0.10984625 | G10: =IFERROR((HistoricalFS!G21/HistoricalFS!F21-1),0) -> 0.028891555 | H10: =IFERROR((HistoricalFS!H21/HistoricalFS!G21-1),0) -> 0.16968909 | J10: =AVERAGE(D10:H10) -> 0.10384896 | K10: =MEDIAN(D10:H10) -> 0.10984625
B11: EBIT Growth | D11: =IFERROR((HistoricalFS!D21-HistoricalFS!D27)/(HistoricalFS!C21-HistoricalFS!C27)-1,0) -> 0.072284405 | E11: =IFERROR((HistoricalFS!E21-HistoricalFS!E27)/(HistoricalFS!D21-HistoricalFS!D27)-1,0) -> 0.12830785 | F11: =IFERROR((HistoricalFS!F21-HistoricalFS!F27)/(HistoricalFS!E21-HistoricalFS!E27)-1,0) -> 0.10893467 | G11: =IFERROR((HistoricalFS!G21-HistoricalFS!G27)/(HistoricalFS!F21-HistoricalFS!F27)-1,0) -> 0.019303865 | H11: =IFERROR((HistoricalFS!H21-HistoricalFS!H27)/(HistoricalFS!G21-HistoricalFS!G27)-1,0) -> 0.15888733 | J11: =AVERAGE(D11:H11) -> 0.097543624 | K11: =MEDIAN(D11:H11) -> 0.10893467
B12: Net Profit Growth | D12: =IFERROR(HistoricalFS!D39/HistoricalFS!C39-1,0) -> 0.040310929 | E12: =IFERROR(HistoricalFS!E39/HistoricalFS!D39-1,0) -> 0.12983065 | F12: =IFERROR(HistoricalFS!F39/HistoricalFS!E39-1,0) -> 0.1588842 | G12: =IFERROR(HistoricalFS!G39/HistoricalFS!F39-1,0) -> 0.044219644 | H12: =IFERROR(HistoricalFS!H39/HistoricalFS!G39-1,0) -> 0.14382432 | J12: =AVERAGE(D12:H12) -> 0.10341395 | K12: =MEDIAN(D12:H12) -> 0.12983065
B13: Dividend Growth | D13: =IFERROR(HistoricalFS!D47/HistoricalFS!C47-1,0) -> 0.12624085 | E13: =IFERROR(HistoricalFS!E47/HistoricalFS!D47-1,0) -> -0.32840335 | F13: =IFERROR(HistoricalFS!F47/HistoricalFS!E47-1,0) -> 0.65930001 | G13: =IFERROR(HistoricalFS!G47/HistoricalFS!F47-1,0) -> 0.19407667 | H13: =IFERROR(HistoricalFS!H47/HistoricalFS!G47-1,0) -> 0.081301811 | J13: =AVERAGE(D13:H13) -> 0.1465032 | K13: =MEDIAN(D13:H13) -> 0.12624085
B15: Gross Margin | C15: =IFERROR(HistoricalFS!C16,0) -> 0.52476722 | D15: =IFERROR(HistoricalFS!D16,0) -> 0.48975258 | E15: =IFERROR(HistoricalFS!E16,0) -> 0.49154848 | F15: =IFERROR(HistoricalFS!F16,0) -> 0.51862945 | G15: =IFERROR(HistoricalFS!G16,0) -> 0.5189803 | H15: =IFERROR(HistoricalFS!H16,0) -> 0.50792037 | J15: =AVERAGE(C15:H15) -> 0.50859973 | K15: =MEDIAN(C15:H15) -> 0.51327491
B16: EBITDA Margin | C16: =IFERROR(HistoricalFS!C22,0) -> 0.14419656 | D16: =IFERROR(HistoricalFS!D22,0) -> 0.12500815 | E16: =IFERROR(HistoricalFS!E22,0) -> 0.13455396 | F16: =IFERROR(HistoricalFS!F22,0) -> 0.14665786 | G16: =IFERROR(HistoricalFS!G22,0) -> 0.1385061 | H16: =IFERROR(HistoricalFS!H22,0) -> 0.1442723 | J16: =AVERAGE(C16:H16) -> 0.13886582 | K16: =MEDIAN(C16:H16) -> 0.14135133
B17: EBIT Margin | C17: =IFERROR((HistoricalFS!C21-HistoricalFS!C27)/HistoricalFS!C9,0) -> 0.13725878 | D17: =IFERROR((HistoricalFS!D21-HistoricalFS!D27)/HistoricalFS!D9,0) -> 0.11805929 | E17: =IFERROR((HistoricalFS!E21-HistoricalFS!E27)/HistoricalFS!E9,0) -> 0.12687884 | F17: =IFERROR((HistoricalFS!F21-HistoricalFS!F27)/HistoricalFS!F9,0) -> 0.13817873 | G17: =IFERROR((HistoricalFS!G21-HistoricalFS!G27)/HistoricalFS!G9,0) -> 0.12928223 | H17: =IFERROR((HistoricalFS!H21-HistoricalFS!H27)/HistoricalFS!H9,0) -> 0.13342083 | J17: =AVERAGE(C17:H17) -> 0.13051311 | K17: =MEDIAN(C17:H17) -> 0.13135153
B18: EBT Margin | C18: =IFERROR(HistoricalFS!C34,0) -> 0.14062265 | D18: =IFERROR(HistoricalFS!D34,0) -> 0.1178548 | E18: =IFERROR(HistoricalFS!E34,0) -> 0.12617979 | F18: =IFERROR(HistoricalFS!F34,0) -> 0.14406986 | G18: =IFERROR(HistoricalFS!G34,0) -> 0.13880536 | H18: =IFERROR(HistoricalFS!H34,0) -> 0.14096333 | J18: =AVERAGE(C18:H18) -> 0.1347493 | K18: =MEDIAN(C18:H18) -> 0.13971401
B19: Net Profit Margin | C19: =IFERROR(HistoricalFS!C40,0) -> 0.10493163 | D19: =IFERROR(HistoricalFS!D40,0) -> 0.087562795 | E19: =IFERROR(HistoricalFS!E40,0) -> 0.094231131 | F19: =IFERROR(HistoricalFS!F40,0) -> 0.10724585 | G19: =IFERROR(HistoricalFS!G40,0) -> 0.10279366 | H19: =IFERROR(HistoricalFS!H40,0) -> 0.10470544 | J19: =AVERAGE(C19:H19) -> 0.10024508 | K19: =MEDIAN(C19:H19) -> 0.10374955
B21: Sales Expense % Revenue | C21: =IFERROR(HistoricalFS!C18/HistoricalFS!C9,0) -> 0.38057066 | D21: =IFERROR(HistoricalFS!D18/HistoricalFS!D9,0) -> 0.36474443 | E21: =IFERROR(HistoricalFS!E18/HistoricalFS!E9,0) -> 0.35699452 | F21: =IFERROR(HistoricalFS!F18/HistoricalFS!F9,0) -> 0.3719716 | G21: =IFERROR(HistoricalFS!G18/HistoricalFS!G9,0) -> 0.3804742 | H21: =IFERROR(HistoricalFS!H18/HistoricalFS!H9,0) -> 0.36364807 | J21: =AVERAGE(C21:H21) -> 0.36973391 | K21: =MEDIAN(C21:H21) -> 0.36835801
B22: Depreciation % Revenue | C22: =IFERROR(HistoricalFS!C27/HistoricalFS!C9,0) -> 0.0069377771 | D22: =IFERROR(HistoricalFS!D27/HistoricalFS!D9,0) -> 0.0069488698 | E22: =IFERROR(HistoricalFS!E27/HistoricalFS!E9,0) -> 0.0076751227 | F22: =IFERROR(HistoricalFS!F27/HistoricalFS!F9,0) -> 0.0084791315 | G22: =IFERROR(HistoricalFS!G27/HistoricalFS!G9,0) -> 0.0092238755 | H22: =IFERROR(HistoricalFS!H27/HistoricalFS!H9,0) -> 0.010851468 | J22: =AVERAGE(C22:H22) -> 0.0083527074 | K22: =MEDIAN(C22:H22) -> 0.0080771271
B23: Operating Income % Revenue | C23: =C17 -> 0.13725878 | D23: =D17 -> 0.11805929 | E23: =E17 -> 0.12687884 | F23: =F17 -> 0.13817873 | G23: =G17 -> 0.12928223 | H23: =H17 -> 0.13342083 | J23: =AVERAGE(C23:H23) -> 0.13051311 | K23: =MEDIAN(C23:H23) -> 0.13135153
B25: Return on Capital Employed (ROCE) | C25: =IFERROR(SUM(HistoricalFS!C33,HistoricalFS!C24)/SUM(HistoricalFS!C74:C75,HistoricalFS!C78),0) -> 0.56207134 | D25: =IFERROR(SUM(HistoricalFS!D33,HistoricalFS!D24)/SUM(HistoricalFS!D74:D75,HistoricalFS!D78),0) -> 0.48056118 | E25: =IFERROR(SUM(HistoricalFS!E33,HistoricalFS!E24)/SUM(HistoricalFS!E74:E75,HistoricalFS!E78),0) -> 0.44382341 | F25: =IFERROR(SUM(HistoricalFS!F33,HistoricalFS!F24)/SUM(HistoricalFS!F74:F75,HistoricalFS!F78),0) -> 0.43838235 | G25: =IFERROR(SUM(HistoricalFS!G33,HistoricalFS!G24)/SUM(HistoricalFS!G74:G75,HistoricalFS!G78),0) -> 0.39493441 | H25: =IFERROR(SUM(HistoricalFS!H33,HistoricalFS!H24)/SUM(HistoricalFS!H74:H75,HistoricalFS!H78),0) -> 0.38685906 | J25: =AVERAGE(C25:H25) -> 0.45110529 | K25: =MEDIAN(C25:H25) -> 0.44110288
B26: Retained Earnings % | C26: =IFERROR(HistoricalFS!C50,0) -> 0.47392408 | D26: =IFERROR(HistoricalFS!D50,0) -> 0.43047009 | E26: =IFERROR(HistoricalFS!E50,0) -> 0.66145866 | F26: =IFERROR(HistoricalFS!F50,0) -> 0.51527371 | G26: =IFERROR(HistoricalFS!G50,0) -> 0.44571015 | H26: =IFERROR(HistoricalFS!H50,0) -> 0.47600815 | J26: =AVERAGE(C26:H26) -> 0.50047414 | K26: =MEDIAN(C26:H26) -> 0.47496612
B27: Return on Equity (ROE) | C27: =IFERROR((HistoricalFS!C39/SUM(HistoricalFS!C74:C75)),0) -> 0.45396747 | D27: =IFERROR((HistoricalFS!D39/SUM(HistoricalFS!D74:D75)),0) -> 0.39349976 | E27: =IFERROR((HistoricalFS!E39/SUM(HistoricalFS!E74:E75)),0) -> 0.34323361 | F27: =IFERROR((HistoricalFS!F39/SUM(HistoricalFS!F74:F75)),0) -> 0.32936228 | G27: =IFERROR((HistoricalFS!G39/SUM(HistoricalFS!G74:G75)),0) -> 0.29926731 | H27: =IFERROR((HistoricalFS!H39/SUM(HistoricalFS!H74:H75)),0) -> 0.29464235 | J27: =AVERAGE(C27:H27) -> 0.3523288 | K27: =MEDIAN(C27:H27) -> 0.33629795
B28: Self Sustained Growth Rate | C28: =IFERROR(C27*C26,0) -> 0.21514612 | D28: =IFERROR(D27*D26,0) -> 0.16938988 | E28: =IFERROR(E27*E26,0) -> 0.22703485 | F28: =IFERROR(F27*F26,0) -> 0.16971173 | G28: =IFERROR(G27*G26,0) -> 0.13338648 | H28: =IFERROR(H27*H26,0) -> 0.14025216 | J28: =AVERAGE(C28:H28) -> 0.1758202 | K28: =MEDIAN(C28:H28) -> 0.1695508
B29: Interest Coverage Ratio | C29: =IFERROR((HistoricalFS!C33+HistoricalFS!C24)/HistoricalFS!C24,0) -> 23.823097 | D29: =IFERROR((HistoricalFS!D33+HistoricalFS!D24)/HistoricalFS!D24,0) -> 19.640323 | E29: =IFERROR((HistoricalFS!E33+HistoricalFS!E24)/HistoricalFS!E24,0) -> 27.096728 | F29: =IFERROR((HistoricalFS!F33+HistoricalFS!F24)/HistoricalFS!F24,0) -> 33.426948 | G29: =IFERROR((HistoricalFS!G33+HistoricalFS!G24)/HistoricalFS!G24,0) -> 54.347456 | H29: =IFERROR((HistoricalFS!H33+HistoricalFS!H24)/HistoricalFS!H24,0) -> 51.050102 | J29: =AVERAGE(C29:H29) -> 34.897442 | K29: =MEDIAN(C29:H29) -> 30.261838
B31: Debtor Turnover Ratio | C31: =IFERROR(HistoricalFS!C9/HistoricalFS!C65,0) -> 19.210092 | D31: =IFERROR(HistoricalFS!D9/HistoricalFS!D65,0) -> 18.134033 | E31: =IFERROR(HistoricalFS!E9/HistoricalFS!E65,0) -> 21.212323 | F31: =IFERROR(HistoricalFS!F9/HistoricalFS!F65,0) -> 21.466998 | G31: =IFERROR(HistoricalFS!G9/HistoricalFS!G65,0) -> 18.291452 | H31: =IFERROR(HistoricalFS!H9/HistoricalFS!H65,0) -> 21.748774 | J31: =AVERAGE(C31:H31) -> 20.010612 | K31: =MEDIAN(C31:H31) -> 20.211207
B32: Creditor Turnover Ratio | C32: =IFERROR(HistoricalFS!C9/SUM(HistoricalFS!C85:C86),0) -> 10.038148 | D32: =IFERROR(HistoricalFS!D9/SUM(HistoricalFS!D85:D86),0) -> 13.284263 | E32: =IFERROR(HistoricalFS!E9/SUM(HistoricalFS!E85:E86),0) -> 16.630456 | F32: =IFERROR(HistoricalFS!F9/SUM(HistoricalFS!F85:F86),0) -> 14.902294 | G32: =IFERROR(HistoricalFS!G9/SUM(HistoricalFS!G85:G86),0) -> 14.106235 | H32: =IFERROR(HistoricalFS!H9/SUM(HistoricalFS!H85:H86),0) -> 12.991228 | J32: =AVERAGE(C32:H32) -> 13.658771 | K32: =MEDIAN(C32:H32) -> 13.695249
B33: Inventory Turnover Ratio | C33: =IFERROR(HistoricalFS!C12/HistoricalFS!C64,0) -> 3.7581268 | D33: =IFERROR(HistoricalFS!D12/HistoricalFS!D64,0) -> 2.7446445 | E33: =IFERROR(HistoricalFS!E12/HistoricalFS!E64,0) -> 3.0159639 | F33: =IFERROR(HistoricalFS!F12/HistoricalFS!F64,0) -> 3.5099465 | G33: =IFERROR(HistoricalFS!G12/HistoricalFS!G64,0) -> 3.5740436 | H33: =IFERROR(HistoricalFS!H12/HistoricalFS!H64,0) -> 3.1950756 | J33: =AVERAGE(C33:H33) -> 3.2996335 | K33: =MEDIAN(C33:H33) -> 3.352511
B34: Fixed Asset Turnover Ratio | C34: =IFERROR(HistoricalFS!C9/HistoricalFS!C54,0) -> 19.74535 | D34: =IFERROR(HistoricalFS!D9/HistoricalFS!D54,0) -> 18.558713 | E34: =IFERROR(HistoricalFS!E9/HistoricalFS!E54,0) -> 15.234725 | F34: =IFERROR(HistoricalFS!F9/HistoricalFS!F54,0) -> 14.233276 | G34: =IFERROR(HistoricalFS!G9/HistoricalFS!G54,0) -> 13.232345 | H34: =IFERROR(HistoricalFS!H9/HistoricalFS!H54,0) -> 10.443193 | J34: =AVERAGE(C34:H34) -> 15.241267 | K34: =MEDIAN(C34:H34) -> 14.734
B35: Capital Turnover Ratio | C35: =IFERROR(HistoricalFS!C9/SUM(HistoricalFS!C74:C75,HistoricalFS!C78),0) -> 3.8292393 | D35: =IFERROR(HistoricalFS!D9/SUM(HistoricalFS!D74:D75,HistoricalFS!D78),0) -> 3.8699577 | E35: =IFERROR(HistoricalFS!E9/SUM(HistoricalFS!E74:E75,HistoricalFS!E78),0) -> 3.3875805 | F35: =IFERROR(HistoricalFS!F9/SUM(HistoricalFS!F74:F75,HistoricalFS!F78),0) -> 2.9518161 | G35: =IFERROR(HistoricalFS!G9/SUM(HistoricalFS!G74:G75,HistoricalFS!G78),0) -> 2.7928861 | H35: =IFERROR(HistoricalFS!H9/SUM(HistoricalFS!H74:H75,HistoricalFS!H78),0) -> 2.6906362 | J35: =AVERAGE(C35:H35) -> 3.253686 | K35: =MEDIAN(C35:H35) -> 3.1696983
B37: Debtor Days | C37: =IFERROR(365/C31,0) -> 19.000429 | D37: =IFERROR(365/D31,0) -> 20.1279 | E37: =IFERROR(365/E31,0) -> 17.20698 | F37: =IFERROR(365/F31,0) -> 17.002843 | G37: =IFERROR(365/G31,0) -> 19.954676 | H37: =IFERROR(365/H31,0) -> 16.782555 | J37: =AVERAGE(C37:H37) -> 18.345897 | K37: =MEDIAN(C37:H37) -> 18.103704
B38: Payable Days | C38: =IFERROR(365/C32,0) -> 36.361288 | D38: =IFERROR(365/D32,0) -> 27.47612 | E38: =IFERROR(365/E32,0) -> 21.947685 | F38: =IFERROR(365/F32,0) -> 24.492874 | G38: =IFERROR(365/G32,0) -> 25.875084 | H38: =IFERROR(365/H32,0) -> 28.095881 | J38: =AVERAGE(C38:H38) -> 27.374822 | K38: =MEDIAN(C38:H38) -> 26.675602
B39: Inventory Days | C39: =IFERROR(365/C33,0) -> 97.122854 | D39: =IFERROR(365/D33,0) -> 132.98626 | E39: =IFERROR(365/E33,0) -> 121.02267 | F39: =IFERROR(365/F33,0) -> 103.99019 | G39: =IFERROR(365/G33,0) -> 102.12522 | H39: =IFERROR(365/H33,0) -> 114.2383 | J39: =AVERAGE(C39:H39) -> 111.91425 | K39: =MEDIAN(C39:H39) -> 109.11424
B40: Cash Conversion Cycle (days) | C40: =IFERROR(C37+C39-C38,0) -> 79.761995 | D40: =IFERROR(D37+D39-D38,0) -> 125.63804 | E40: =IFERROR(E37+E39-E38,0) -> 116.28196 | F40: =IFERROR(F37+F39-F38,0) -> 96.500159 | G40: =IFERROR(G37+G39-G38,0) -> 96.204816 | H40: =IFERROR(H37+H39-H38,0) -> 102.92497 | J40: =AVERAGE(C40:H40) -> 102.88532 | K40: =MEDIAN(C40:H40) -> 99.712565
B42: CFO/Sales | C42: =IFERROR(HistoricalFS!C98/HistoricalFS!C9,0) -> 0.24586738 | D42: =IFERROR(HistoricalFS!D98/HistoricalFS!D9,0) -> -0.054437215 | E42: =IFERROR(HistoricalFS!E98/HistoricalFS!E9,0) -> 0.091733504 | F42: =IFERROR(HistoricalFS!F98/HistoricalFS!F9,0) -> 0.17015081 | G42: =IFERROR(HistoricalFS!G98/HistoricalFS!G9,0) -> 0.091339366 | H42: =IFERROR(HistoricalFS!H98/HistoricalFS!H9,0) -> 0.069911 | J42: =AVERAGE(C42:H42) -> 0.10242747 | K42: =MEDIAN(C42:H42) -> 0.091536435
B43: CFO/Total Assets | C43: =IFERROR(HistoricalFS!C98/HistoricalFS!C71,0) -> 0.48193291 | D43: =IFERROR(HistoricalFS!D98/HistoricalFS!D71,0) -> -0.12727552 | E43: =IFERROR(HistoricalFS!E98/HistoricalFS!E71,0) -> 0.20040975 | F43: =IFERROR(HistoricalFS!F98/HistoricalFS!F71,0) -> 0.33116616 | G43: =IFERROR(HistoricalFS!G98/HistoricalFS!G71,0) -> 0.17453538 | H43: =IFERROR(HistoricalFS!H98/HistoricalFS!H71,0) -> 0.12727542 | J43: =AVERAGE(C43:H43) -> 0.19800735 | K43: =MEDIAN(C43:H43) -> 0.18747256
B44: CFO/Total Debt | C44: =IFERROR(HistoricalFS!C98/SUM(HistoricalFS!C78,HistoricalFS!C84),0) -> 5.0346571 | D44: =IFERROR(HistoricalFS!D98/SUM(HistoricalFS!D78,HistoricalFS!D84),0) -> -1.2016945 | E44: =IFERROR(HistoricalFS!E98/SUM(HistoricalFS!E78,HistoricalFS!E84),0) -> 2.1806152 | F44: =IFERROR(HistoricalFS!F98/SUM(HistoricalFS!F78,HistoricalFS!F84),0) -> 5.5569519 | G44: =IFERROR(HistoricalFS!G98/SUM(HistoricalFS!G78,HistoricalFS!G84),0) -> 4.4067793 | H44: =IFERROR(HistoricalFS!H98/SUM(HistoricalFS!H78,HistoricalFS!H84),0) -> 2.9805738 | J44: =AVERAGE(C44:H44) -> 3.1596471 | K44: =MEDIAN(C44:H44) -> 3.6936765

Sheet Forecasting
B2: Hawkins Cookers Limited
O4: (Values in Rs. Lakhs)
B7: Hawkins Cookers Limited - Revenue Forecasting | G7: Hawkins Cookers Limited - EBITDA Forecasting | L7: Hawkins Cookers Limited - Net Profit Forecasting
B8: Year Weight | C8: Year | D8: Revenue | E8: Growth | G8: Year Weight | H8: Year | I8: EBITDA | J8: Growth | L8: Year Weight | M8: Year | N8: Net Profit | O8: Growth
B9: 1 | C9: 2021 | D9: {=TRANSPOSE(HistoricalFS!C9:H9)} -> 76845.94 | G9: 1 | H9: 2021 | I9: {=TRANSPOSE(HistoricalFS!C21:H21)} -> 11080.92 | L9: 1 | M9: 2021 | N9: {=TRANSPOSE(HistoricalFS!C39:H39)} -> 8063.57
B10: =B9+1 -> 2 | C10: =C9+1 -> 2022 | D10: 95801.19 | E10: =D10/D9-1 -> 0.2466656 | G10: =G9+1 -> 2 | H10: =H9+1 -> 2022 | I10: 11975.93 | J10: =I10/I9-1 -> 0.080770369 | L10: =L9+1 -> 2 | M10: =M9+1 -> 2022 | N10: 8388.62 | O10: =N10/N9-1 -> 0.040310929
B11: =B10+1 -> 3 | C11: =C10+1 -> 2023 | D11: 100579.5 | E11: =D11/D10-1 -> 0.049877355 | G11: =G10+1 -> 3 | H11: =H10+1 -> 2023 | I11: 13533.37 | J11: =I11/I10-1 -> 0.13004752 | L11: =L10+1 -> 3 | M11: =M10+1 -> 2023 | N11: 9477.72 | O11: =N11/N10-1 -> 0.12983065
B12: =B11+1 -> 4 | C12: =C11+1 -> 2024 | D12: 102414.97 | E12: =D12/D11-1 -> 0.018248947 | G12: =G11+1 -> 4 | H12: =H11+1 -> 2024 | I12: 15019.96 | J12: =I12/I11-1 -> 0.10984625 | L12: =L11+1 -> 4 | M12: =M11+1 -> 2024 | N12: 10983.58 | O12: =N12/N11-1 -> 0.1588842
B13: =B12+1 -> 5 | C13: =C12+1 -> 2025 | D13: 111575.66 | E13: =D13/D12-1 -> 0.089446787 | G13: =G12+1 -> 5 | H13: =H12+1 -> 2025 | I13: 15453.91 | J13: =I13/I12-1 -> 0.028891555 | L13: =L12+1 -> 5 | M13: =M12+1 -> 2025 | N13: 11469.27 | O13: =N13/N12-1 -> 0.044219644
B14: =B13+1 -> 6 | C14: =C13+1 -> 2026 | D14: 125292.73 | E14: =D14/D13-1 -> 0.12293963 | G14: =G13+1 -> 6 | H14: =H13+1 -> 2026 | I14: 18076.27 | J14: =I14/I13-1 -> 0.16968909 | L14: =L13+1 -> 6 | M14: =M13+1 -> 2026 | N14: 13118.83 | O14: =N14/N13-1 -> 0.14382432
B15: =B14+1 -> 7 | C15: =C14+1 -> 2027 | D15: =FORECAST(B15,$D$9:$D$14,$B$9:$B$14) -> 131224.28 | E15: =D15/D14-1 -> 0.047341544 | G15: =G14+1 -> 7 | H15: =H14+1 -> 2027 | I15: =FORECAST(G15,$I$9:$I$14,$G$9:$G$14) -> 18879.788 | J15: =I15/I14-1 -> 0.044451538 | L15: =L14+1 -> 7 | M15: =M14+1 -> 2027 | N15: =FORECAST(L15,$N$9:$N$14,$L$9:$L$14) -> 13852.676 | O15: =N15/N14-1 -> 0.055938373
B16: =B15+1 -> 8 | C16: =C15+1 -> 2028 | D16: =FORECAST(B16,$D$9:$D$14,$B$9:$B$14) -> 139549.79 | E16: =D16/D15-1 -> 0.063444885 | G16: =G15+1 -> 8 | H16: =H15+1 -> 2028 | I16: =FORECAST(G16,$I$9:$I$14,$G$9:$G$14) -> 20219.71 | J16: =I16/I15-1 -> 0.070971257 | L16: =L15+1 -> 8 | M16: =M15+1 -> 2028 | N16: =FORECAST(L16,$N$9:$N$14,$L$9:$L$14) -> 14881.936 | O16: =N16/N15-1 -> 0.074300466
B17: =B16+1 -> 9 | C17: =C16+1 -> 2029 | D17: =FORECAST(B17,$D$9:$D$14,$B$9:$B$14) -> 147875.3 | E17: =D17/D16-1 -> 0.059659777 | G17: =G16+1 -> 9 | H17: =H16+1 -> 2029 | I17: =FORECAST(G17,$I$9:$I$14,$G$9:$G$14) -> 21559.633 | J17: =I17/I16-1 -> 0.066268125 | L17: =L16+1 -> 9 | M17: =M16+1 -> 2029 | N17: =FORECAST(L17,$N$9:$N$14,$L$9:$L$14) -> 15911.197 | O17: =N17/N16-1 -> 0.069161718
B18: =B17+1 -> 10 | C18: =C17+1 -> 2030 | D18: =FORECAST(B18,$D$9:$D$14,$B$9:$B$14) -> 156200.81 | E18: =D18/D17-1 -> 0.056300879 | G18: =G17+1 -> 10 | H18: =H17+1 -> 2030 | I18: =FORECAST(G18,$I$9:$I$14,$G$9:$G$14) -> 22899.555 | J18: =I18/I17-1 -> 0.062149588 | L18: =L17+1 -> 10 | M18: =M17+1 -> 2030 | N18: =FORECAST(L18,$N$9:$N$14,$L$9:$L$14) -> 16940.457 | O18: =N18/N17-1 -> 0.064687799
B19: =B18+1 -> 11 | C19: =C18+1 -> 2031 | D19: =FORECAST(B19,$D$9:$D$14,$B$9:$B$14) -> 164526.32 | E19: =D19/D18-1 -> 0.05330004 | G19: =G18+1 -> 11 | H19: =H18+1 -> 2031 | I19: =FORECAST(G19,$I$9:$I$14,$G$9:$G$14) -> 24239.477 | J19: =I19/I18-1 -> 0.058513028 | L19: =L18+1 -> 11 | M19: =M18+1 -> 2031 | N19: =FORECAST(L19,$N$9:$N$14,$L$9:$L$14) -> 17969.717 | O19: =N19/N18-1 -> 0.060757528
C22: Revenue | H22: EBITDA | M22: Net Profit

Sheet WACC
B2: Hawkins Cookers Limited
B7: Weighted Average Cost of Capital
B9: All figures are in INR unless stated otherwise.
B11: Peer Companies | I11: (Values in Rs. Crore)
G12: Debt / | H12: Debt / | I12: Levered | J12: Unlevered
B13: Name | C13: Country | D13: Total Debt | E13: Total Equity | F13: Tax Rate 1 | G13: Equity | H13: Capital | I13: Beta 2 | J13: Beta 3
B15: Cello World | C15: India | D15: ='Beta - Comps'!F7 -> 38.11 | E15: ='Beta - Comps'!E7 -> 8340.62 | F15: 0.3 | G15: =D15/E15 -> 0.0045692047 | H15: =D15/(E15+D15) -> 0.004548422 | I15: 1.18 | J15: =I15/1+(1-F15)*G15 -> 1.1831984
B16: Borosil | C16: India | D16: ='Beta - Comps'!F9 -> 148.08 | E16: ='Beta - Comps'!E9 -> 2852.76 | F16: 0.3 | G16: =D16/E16 -> 0.051907626 | H16: =D16/(E16+D16) -> 0.049346183 | I16: 1.29 | J16: =I16/1+(1-F16)*G16 -> 1.3263353
B17: All Time Plastic | C17: India | D17: ='Beta - Comps'!F10 -> 86.4 | E17: ='Beta - Comps'!E10 -> 1411.95 | F17: 0.3 | G17: =D17/E17 -> 0.061191969 | H17: =D17/(E17+D17) -> 0.05766343 | I17: 0.52 | J17: =I17/1+(1-F17)*G17 -> 0.56283438
B18: Clay Craft India | C18: India | D18: 49.98 | E18: 332.42 | F18: 0.3 | G18: =D18/E18 -> 0.15035196 | H18: =D18/(E18+D18) -> 0.13070084 | I18: 0.82 | J18: =I18/1+(1-F18)*G18 -> 0.92524638
B19: Hawkins Cookers | C19: India | D19: ='Beta - Comps'!F8 -> 29.39 | E19: ='Beta - Comps'!E8 -> 4417.68 | F19: 0.3 | G19: =D19/E19 -> 0.0066528132 | H19: =D19/(E19+D19) -> 0.0066088458 | I19: ='Beta - Regression'!M13 -> 0.18276103 | J19: =I19/1+(1-F19)*G19 -> 0.18741799
E21: Average | F21: =AVERAGE(F15:F19) -> 0.3 | G21: =AVERAGE(G15:G19) -> 0.054934715 | H21: =AVERAGE(H15:H19) -> 0.049773544 | I21: =AVERAGE(I15:I19) -> 0.79855221 | J21: =AVERAGE(J15:J19) -> 0.83700651
E22: Median | F22: =MEDIAN(F15:F19) -> 0.3 | G22: =MEDIAN(G15:G19) -> 0.051907626 | H22: =MEDIAN(H15:H19) -> 0.049346183 | I22: =MEDIAN(I15:I19) -> 0.82 | J22: =MEDIAN(J15:J19) -> 0.92524638
B25: Cost of Debt | G25: Cost of Equity
B27: Pre-tax Cost of Debt | E27: =HistoricalFS!H24/(SUM(HistoricalFS!H78,HistoricalFS!H84)) -> 0.12007581 | G27: Risk Free Rate | J27: 0.0676
B28: Tax Rate | E28: =F22 -> 0.3 | G28: Equity Risk Premium | J28: =Rm!F13-J27 -> 0.096892308
B29: After Tax Cost of Debt | E29: =E27*(1-E28) -> 0.084053069 | G29: Levered Beta 4 | J29: =J38 -> 1.1884121
G30: Cost of Equity | J30: =J27+(J28)*J29 -> 0.18274799
B33: Capital Structure | G33: Levered Beta
D35: Current | E35: Target | G35: Comps Median Unlevered Beta | J35: =J22 -> 0.92524638
B36: Total Debt | C36: =D19 -> 29.39 | D36: =C36/$C$38 -> 0.0066088458 | E36: =H22 -> 0.049346183 | G36: Target Debt/Equity | J36: =E40 -> 0.051907626
B37: Market Capitalization | C37: =E19 -> 4417.68 | D37: =100%-D36 -> 0.99339115 | E37: =E38-E36 -> 0.95065382 | G37: Tax Rate | J37: =F22 -> 0.3
B38: Total Capitalization | C38: =C36+C37 -> 4447.07 | D38: =D37+D36 -> 1 | E38: =D38 -> 1 | G38: Levered Beta | J38: =J35*(1+(1-J36)*J37) -> 1.1884121
B40: Debt / Equity | D40: =D36/D37 -> 0.0066528132 | E40: =E36/E37 -> 0.051907626 | G40: Weighted Average Cost of Capital
G42: Cost of Equity | J42: =J30 -> 0.18274799
G43: Equity Weight | J43: =E37 -> 0.95065382
B45: 1. Tax Rate considered as Marginal Tax Rate for the Country | G45: Cost of Debt | J45: =E29 -> 0.084053069
B46: 2. Levered Beta is based on 2 year daily data | G46: Debt Weight | J46: =E36 -> 0.049346183
B47: 3. Unlevered Beta = Levered Beta/(1+(1-Tax Rate) x Debt/Equity)
B48: 4. Levered Beta = Unlevered Beta*(1+(1-Tax Rate) x Debt/Equity | G48: WACC | J48: =(J42*J43)+(J45*J46) -> 0.17787777

Sheet Common Size Statement
B2: Hawkins Cookers Limited
B6: Common Size Income Statement - Hawkins Cookers Limited
B8: Particulars | C8: =HistoricalFS!C7 -> 2021 | D8: =HistoricalFS!D7 -> 2022 | E8: =HistoricalFS!E7 -> 2023 | F8: =HistoricalFS!F7 -> 2024 | G8: =HistoricalFS!G7 -> 2025 | H8: =HistoricalFS!H7 -> 2026
B10: ='Income Statement'!A5 -> Revenue from operations (net) | C10: ='Income Statement'!B5/'Income Statement'!B$5 -> 1 | D10: ='Income Statement'!C5/'Income Statement'!C$5 -> 1 | E10: ='Income Statement'!D5/'Income Statement'!D$5 -> 1 | F10: ='Income Statement'!E5/'Income Statement'!E$5 -> 1 | G10: ='Income Statement'!F5/'Income Statement'!F$5 -> 1 | H10: ='Income Statement'!G5/'Income Statement'!G$5 -> 1
B11: ='Income Statement'!A6 -> Other Income | C11: ='Income Statement'!B6/'Income Statement'!B$5 -> 0.0095252918 | D11: ='Income Statement'!C6/'Income Statement'!C$5 -> 0.0061180868 | E11: ='Income Statement'!D6/'Income Statement'!D$5 -> 0.0041360317 | F11: ='Income Statement'!E6/'Income Statement'!E$5 -> 0.010334036 | G11: ='Income Statement'!F6/'Income Statement'!F$5 -> 0.012125046 | H11: ='Income Statement'!G6/'Income Statement'!G$5 -> 0.010358941
B12: ='Income Statement'!A9 -> Cost of materials consumed | C12: ='Income Statement'!B9/'Income Statement'!B5 -> 0.3202652 | D12: ='Income Statement'!C9/'Income Statement'!C5 -> 0.41041192 | E12: ='Income Statement'!D9/'Income Statement'!D5 -> 0.40231339 | F12: ='Income Statement'!E9/'Income Statement'!E5 -> 0.34528692 | G12: ='Income Statement'!F9/'Income Statement'!F5 -> 0.37990275 | H12: ='Income Statement'!G9/'Income Statement'!G5 -> 0.38830298
B13: ='Income Statement'!A10 -> Purchases of Stock-in-Trade | C13: ='Income Statement'!B10/'Income Statement'!B5 -> 0.10911702 | D13: ='Income Statement'!C10/'Income Statement'!C5 -> 0.15660933 | E13: ='Income Statement'!D10/'Income Statement'!D5 -> 0.10460859 | F13: ='Income Statement'!E10/'Income Statement'!E5 -> 0.11832548 | G13: ='Income Statement'!F10/'Income Statement'!F5 -> 0.10588465 | H13: ='Income Statement'!G10/'Income Statement'!G5 -> 0.11482095
B14: Changes in inventories of Finished Goods, Work-in-Progress and Stock-in-Trade | C14: ='Income Statement'!B11/'Income Statement'!B5 -> 0.045850568 | D14: ='Income Statement'!C11/'Income Statement'!C5 -> -0.056773825 | E14: ='Income Statement'!D11/'Income Statement'!D5 -> 0.0015295363 | F14: ='Income Statement'!E11/'Income Statement'!E5 -> 0.017758146 | G14: ='Income Statement'!F11/'Income Statement'!F5 -> -0.0047677065 | H14: ='Income Statement'!G11/'Income Statement'!G5 -> -0.011044296
B15: ='Income Statement'!A12 -> Employee benefits expense | C15: ='Income Statement'!B12/'Income Statement'!B5 -> 0.13136478 | D15: ='Income Statement'!C12/'Income Statement'!C5 -> 0.11083965 | E15: ='Income Statement'!D12/'Income Statement'!D5 -> 0.11208576 | F15: ='Income Statement'!E12/'Income Statement'!E5 -> 0.11296503 | G15: ='Income Statement'!F12/'Income Statement'!F5 -> 0.10978918 | H15: ='Income Statement'!G12/'Income Statement'!G5 -> 0.10266134
B16: ='Income Statement'!A13 -> Finance costs | C16: ='Income Statement'!B13/'Income Statement'!B5 -> 0.0061614185 | D16: ='Income Statement'!C13/'Income Statement'!C5 -> 0.0063225728 | E16: ='Income Statement'!D13/'Income Statement'!D5 -> 0.0048350807 | F16: ='Income Statement'!E13/'Income Statement'!E5 -> 0.0044429052 | G16: ='Income Statement'!F13/'Income Statement'!F5 -> 0.0026019116 | H16: ='Income Statement'!G13/'Income Statement'!G5 -> 0.0028164443
B17: ='Income Statement'!A14 -> Depreciation and amortization expense | C17: ='Income Statement'!B14/'Income Statement'!B5 -> 0.0069377771 | D17: ='Income Statement'!C14/'Income Statement'!C5 -> 0.0069488698 | E17: ='Income Statement'!D14/'Income Statement'!D5 -> 0.0076751227 | F17: ='Income Statement'!E14/'Income Statement'!E5 -> 0.0084791315 | G17: ='Income Statement'!F14/'Income Statement'!F5 -> 0.0092238755 | H17: ='Income Statement'!G14/'Income Statement'!G5 -> 0.010851468
B18: ='Income Statement'!A15 -> Other expenses | C18: ='Income Statement'!B15/'Income Statement'!B5 -> 0.24920588 | D18: ='Income Statement'!C15/'Income Statement'!C5 -> 0.25390478 | E18: ='Income Statement'!D15/'Income Statement'!D5 -> 0.24490875 | F18: ='Income Statement'!E15/'Income Statement'!E5 -> 0.25900657 | G18: ='Income Statement'!F15/'Income Statement'!F5 -> 0.27068502 | H18: ='Income Statement'!G15/'Income Statement'!G5 -> 0.26098673
B19: ='Income Statement'!A17 -> Profit before tax | C19: ='Income Statement'!B17/'Income Statement'!B5 -> 0.14062239 | D19: ='Income Statement'!C17/'Income Statement'!C5 -> 0.1178549 | E19: ='Income Statement'!D17/'Income Statement'!D5 -> 0.12617969 | F19: ='Income Statement'!E17/'Income Statement'!E5 -> 0.14406995 | G19: ='Income Statement'!F17/'Income Statement'!F5 -> 0.13880536 | H19: ='Income Statement'!G17/'Income Statement'!G5 -> 0.14096333
B20: ='Income Statement'!A19 -> Current tax | C20: ='Income Statement'!B19/'Income Statement'!B5 -> 0.034940037 | D20: ='Income Statement'!C19/'Income Statement'!C5 -> 0.029509028 | E20: ='Income Statement'!D19/'Income Statement'!D5 -> 0.032685885 | F20: ='Income Statement'!E19/'Income Statement'!E5 -> 0.036703619 | G20: ='Income Statement'!F19/'Income Statement'!F5 -> 0.034946063 | H20: ='Income Statement'!G19/'Income Statement'!G5 -> 0.035620582
B21: ='Income Statement'!A20 -> Deferred tax | C21: ='Income Statement'!B20/'Income Statement'!B5 -> 0.00075098307 | D21: ='Income Statement'!C20/'Income Statement'!C5 -> 0.00078297566 | E21: ='Income Statement'!D20/'Income Statement'!D5 -> -0.00073722777 | F21: ='Income Statement'!E20/'Income Statement'!E5 -> 0.00012039256 | G21: ='Income Statement'!F20/'Income Statement'!F5 -> 0.0010656446 | H21: ='Income Statement'!G20/'Income Statement'!G5 -> 0.00063730753
B22: ='Income Statement'!A21 -> Profit for the year (A) | C22: ='Income Statement'!B21/'Income Statement'!B5 -> 0.10493137 | D22: ='Income Statement'!C21/'Income Statement'!C5 -> 0.0875629 | E22: ='Income Statement'!D21/'Income Statement'!D5 -> 0.094231031 | F22: ='Income Statement'!E21/'Income Statement'!E5 -> 0.10724604 | G22: ='Income Statement'!F21/'Income Statement'!F5 -> 0.10279366 | H22: ='Income Statement'!G21/'Income Statement'!G5 -> 0.10470544
B23: EBITDA | C23: =HistoricalFS!C21/HistoricalFS!C9 -> 0.14419656 | D23: =HistoricalFS!D21/HistoricalFS!D9 -> 0.12500815 | E23: =HistoricalFS!E21/HistoricalFS!E9 -> 0.13455396 | F23: =HistoricalFS!F21/HistoricalFS!F9 -> 0.14665786 | G23: =HistoricalFS!G21/HistoricalFS!G9 -> 0.1385061 | H23: =HistoricalFS!H21/HistoricalFS!H9 -> 0.1442723
B25: Common Size Balance Sheet - Hawkins Cookers Limited
B27: Particulars | C27: 2021 | D27: 2022 | E27: 2023 | F27: 2024 | G27: 2025 | H27: 2026
B29: =HistoricalFS!B53 -> NON-CURRENT ASSETS
B30: =HistoricalFS!B54 -> Property, Plant and Equipment | C30: =HistoricalFS!C54/HistoricalFS!C$71 -> 0.099270644 | D30: =HistoricalFS!D54/HistoricalFS!D$71 -> 0.12597986 | E30: =HistoricalFS!E54/HistoricalFS!E$71 -> 0.14340234 | F30: =HistoricalFS!F54/HistoricalFS!F$71 -> 0.13674362 | G30: =HistoricalFS!G54/HistoricalFS!G$71 -> 0.14440714 | H30: =HistoricalFS!H54/HistoricalFS!H$71 -> 0.17432743
B31: =HistoricalFS!B55 -> Capital Work-in-Progress | C31: =HistoricalFS!C55/HistoricalFS!C$71 -> 0.0070905234 | D31: =HistoricalFS!D55/HistoricalFS!D$71 -> 0.0078854861 | E31: =HistoricalFS!E55/HistoricalFS!E$71 -> 0.0046906669 | F31: =HistoricalFS!F55/HistoricalFS!F$71 -> 0.022581114 | G31: =HistoricalFS!G55/HistoricalFS!G$71 -> 0.038450104 | H31: =HistoricalFS!H55/HistoricalFS!H$71 -> 0.017363361
B32: =HistoricalFS!B56 -> Intangible assets | C32: =HistoricalFS!C56/HistoricalFS!C$71 -> 0.00024206442 | D32: =HistoricalFS!D56/HistoricalFS!D$71 -> 0.00041952123 | E32: =HistoricalFS!E56/HistoricalFS!E$71 -> 0.00033189808 | F32: =HistoricalFS!F56/HistoricalFS!F$71 -> 0.00022557928 | G32: =HistoricalFS!G56/HistoricalFS!G$71 -> 0.00078745363 | H32: =HistoricalFS!H56/HistoricalFS!H$71 -> 0.0010017156
B33: =HistoricalFS!B57 -> Investments | C33: =HistoricalFS!C57/HistoricalFS!C$71 -> 6.3768287e-06 | D33: =HistoricalFS!D57/HistoricalFS!D$71 -> 6.1012396e-06 | E33: =HistoricalFS!E57/HistoricalFS!E$71 -> 5.4302696e-06 | F33: =HistoricalFS!F57/HistoricalFS!F$71 -> 4.751038e-06 | G33: =HistoricalFS!G57/HistoricalFS!G$71 -> 4.2815008e-06 | H33: =HistoricalFS!H57/HistoricalFS!H$71 -> 3.6325631e-06
B34: =HistoricalFS!B58 -> Other non-current financial assets | C34: =HistoricalFS!C58/HistoricalFS!C$71 -> 0.028303427 | D34: =HistoricalFS!D58/HistoricalFS!D$71 -> 0.0031841149 | E34: =HistoricalFS!E58/HistoricalFS!E$71 -> 0.016928105 | F34: =HistoricalFS!F58/HistoricalFS!F$71 -> 0.0084728111 | G34: =HistoricalFS!G58/HistoricalFS!G$71 -> 0.016030624 | H34: =HistoricalFS!H58/HistoricalFS!H$71 -> 0.0078919612
B35: =HistoricalFS!B59 -> Non-current tax assets (net) | C35: =HistoricalFS!C59/HistoricalFS!C$71 -> 0.0053213361 | D35: =HistoricalFS!D59/HistoricalFS!D$71 -> 0.0077292943 | E35: =HistoricalFS!E59/HistoricalFS!E$71 -> 0.0064311769 | F35: =HistoricalFS!F59/HistoricalFS!F$71 -> 0.0059895386 | G35: =HistoricalFS!G59/HistoricalFS!G$71 -> 0.0075911009 | H35: =HistoricalFS!H59/HistoricalFS!H$71 -> 0.0061279886
B36: =HistoricalFS!B60 -> Deferred tax assets (net) | C36: =HistoricalFS!C60/HistoricalFS!C$71 -> 0.0021882726 | D36: =HistoricalFS!D60/HistoricalFS!D$71 -> 0.00088589999 | E36: =HistoricalFS!E60/HistoricalFS!E$71 -> 0.0024718587 | F36: =HistoricalFS!F60/HistoricalFS!F$71 -> 0.0016778766 | G36: =HistoricalFS!G60/HistoricalFS!G$71 -> 0.00032488028 | H36: =HistoricalFS!H60/HistoricalFS!H$71 -> 0
B37: =HistoricalFS!B61 -> Other non-current assets | C37: =HistoricalFS!C61/HistoricalFS!C$71 -> 0.0093094048 | D37: =HistoricalFS!D61/HistoricalFS!D$71 -> 0.012722793 | E37: =HistoricalFS!E61/HistoricalFS!E$71 -> 0.012078657 | F37: =HistoricalFS!F61/HistoricalFS!F$71 -> 0.013001691 | G37: =HistoricalFS!G61/HistoricalFS!G$71 -> 0.010719679 | H37: =HistoricalFS!H61/HistoricalFS!H$71 -> 0.0097191404
B38: =HistoricalFS!B63 -> CURRENT ASSETS
B39: =HistoricalFS!B64 -> Inventories | C39: =HistoricalFS!C64/HistoricalFS!C$71 -> 0.2478681 | D39: =HistoricalFS!D64/HistoricalFS!D$71 -> 0.43465402 | E39: =HistoricalFS!E64/HistoricalFS!E$71 -> 0.36831064 | F39: =HistoricalFS!F64/HistoricalFS!F$71 -> 0.26692605 | G39: =HistoricalFS!G64/HistoricalFS!G$71 -> 0.25717485 | H39: =HistoricalFS!H64/HistoricalFS!H$71 -> 0.28038403
B40: =HistoricalFS!B65 -> Trade receivables | C40: =HistoricalFS!C65/HistoricalFS!C$71 -> 0.10203666 | D40: =HistoricalFS!D65/HistoricalFS!D$71 -> 0.12893017 | E40: =HistoricalFS!E65/HistoricalFS!E$71 -> 0.1029918 | F40: =HistoricalFS!F65/HistoricalFS!F$71 -> 0.090665199 | G40: =HistoricalFS!G65/HistoricalFS!G$71 -> 0.10446656 | H40: =HistoricalFS!H65/HistoricalFS!H$71 -> 0.083707475
B41: =HistoricalFS!B66 -> Cash and cash equivalents | C41: =HistoricalFS!C66/HistoricalFS!C$71 -> 0.054421642 | D41: =HistoricalFS!D66/HistoricalFS!D$71 -> 0.0076978119 | E41: =HistoricalFS!E66/HistoricalFS!E$71 -> 0.024855647 | F41: =HistoricalFS!F66/HistoricalFS!F$71 -> 0.022922998 | G41: =HistoricalFS!G66/HistoricalFS!G$71 -> 0.01839778 | H41: =HistoricalFS!H66/HistoricalFS!H$71 -> 0.022804504
B42: =HistoricalFS!B67 -> Bank balances other than above | C42: =HistoricalFS!C67/HistoricalFS!C$71 -> 0.37176095 | D42: =HistoricalFS!D67/HistoricalFS!D$71 -> 0.1512734 | E42: =HistoricalFS!E67/HistoricalFS!E$71 -> 0.18919798 | F42: =HistoricalFS!F67/HistoricalFS!F$71 -> 0.33502173 | G42: =HistoricalFS!G67/HistoricalFS!G$71 -> 0.30655648 | H42: =HistoricalFS!H67/HistoricalFS!H$71 -> 0.25460867
B43: =HistoricalFS!B68 -> Other current financial assets | C43: =HistoricalFS!C68/HistoricalFS!C$71 -> 0.013352314 | D43: =HistoricalFS!D68/HistoricalFS!D$71 -> 0.0059077083 | E43: =HistoricalFS!E68/HistoricalFS!E$71 -> 0.005149416 | F43: =HistoricalFS!F68/HistoricalFS!F$71 -> 0.0093297084 | G43: =HistoricalFS!G68/HistoricalFS!G$71 -> 0.010150753 | H43: =HistoricalFS!H68/HistoricalFS!H$71 -> 0.0066024013
B44: =HistoricalFS!B69 -> Other current assets | C44: =HistoricalFS!C69/HistoricalFS!C$71 -> 0.058828286 | D44: =HistoricalFS!D69/HistoricalFS!D$71 -> 0.11272382 | E44: =HistoricalFS!E69/HistoricalFS!E$71 -> 0.12315439 | F44: =HistoricalFS!F69/HistoricalFS!F$71 -> 0.086437345 | G44: =HistoricalFS!G69/HistoricalFS!G$71 -> 0.084938297 | H44: =HistoricalFS!H69/HistoricalFS!H$71 -> 0.13545769
B46: =HistoricalFS!B71 -> TOTAL ASSETS | C46: =HistoricalFS!C71/HistoricalFS!C71 -> 1 | D46: =HistoricalFS!D71/HistoricalFS!D71 -> 1 | E46: =HistoricalFS!E71/HistoricalFS!E71 -> 1 | F46: =HistoricalFS!F71/HistoricalFS!F71 -> 1 | G46: =HistoricalFS!G71/HistoricalFS!G71 -> 1 | H46: =HistoricalFS!H71/HistoricalFS!H71 -> 1
B48: =HistoricalFS!B73 -> EQUITY
B49: =HistoricalFS!B74 -> Equity Share Capital | C49: =HistoricalFS!C74/HistoricalFS!C$92 -> 0.013487758 | D49: =HistoricalFS!D74/HistoricalFS!D$92 -> 0.012904857 | E49: =HistoricalFS!E74/HistoricalFS!E$92 -> 0.011485674 | F49: =HistoricalFS!F74/HistoricalFS!F$92 -> 0.010049012 | G49: =HistoricalFS!G74/HistoricalFS!G$92 -> 0.009055888 | H49: =HistoricalFS!H74/HistoricalFS!H$92 -> 0.0076833101
B50: =HistoricalFS!B75 -> Other Equity | C50: =HistoricalFS!C75/HistoricalFS!C$92 -> 0.43958439 | D50: =HistoricalFS!D75/HistoricalFS!D$92 -> 0.50735968 | E50: =HistoricalFS!E75/HistoricalFS!E$92 -> 0.58829924 | F50: =HistoricalFS!F75/HistoricalFS!F$92 -> 0.62370159 | G50: =HistoricalFS!G75/HistoricalFS!G$92 -> 0.64728962 | H50: =HistoricalFS!H75/HistoricalFS!H$92 -> 0.63927049
B51: =HistoricalFS!B77 -> NON-CURRENT LIABILITIES
B52: =HistoricalFS!B78 -> Borrowings | C52: =HistoricalFS!C78/HistoricalFS!C$92 -> 0.058813747 | D52: =HistoricalFS!D78/HistoricalFS!D$92 -> 0.083882791 | E52: =HistoricalFS!E78/HistoricalFS!E$92 -> 0.045128374 | F52: =HistoricalFS!F78/HistoricalFS!F$92 -> 0.025609225 | G52: =HistoricalFS!G78/HistoricalFS!G$92 -> 0.027837462 | H52: =HistoricalFS!H78/HistoricalFS!H$92 -> 0.029665266
B53: =HistoricalFS!B79 -> Other non-current financial liabilities | C53: =HistoricalFS!C79/HistoricalFS!C$92 -> 0 | D53: =HistoricalFS!D79/HistoricalFS!D$92 -> 0 | E53: =HistoricalFS!E79/HistoricalFS!E$92 -> 0.0027144837 | F53: =HistoricalFS!F79/HistoricalFS!F$92 -> 0.0009743425 | G53: =HistoricalFS!G79/HistoricalFS!G$92 -> 0.0013111668 | H53: =HistoricalFS!H79/HistoricalFS!H$92 -> 0.001529455
B54: =HistoricalFS!B80 -> Provisions | C54: =HistoricalFS!C80/HistoricalFS!C$92 -> 0.014336897 | D54: =HistoricalFS!D80/HistoricalFS!D$92 -> 0.015091786 | E54: =HistoricalFS!E80/HistoricalFS!E$92 -> 0.018330856 | F54: =HistoricalFS!F80/HistoricalFS!F$92 -> 0.017021822 | G54: =HistoricalFS!G80/HistoricalFS!G$92 -> 0.014229311 | H54: =HistoricalFS!H80/HistoricalFS!H$92 -> 0.011521769
B55: =HistoricalFS!B81 -> Deferred tax liabilities (net) | C55: =HistoricalFS!C81/HistoricalFS!C$92 -> 0 | D55: =HistoricalFS!D81/HistoricalFS!D$92 -> 0 | E55: =HistoricalFS!E81/HistoricalFS!E$92 -> 0 | F55: =HistoricalFS!F81/HistoricalFS!F$92 -> 0 | G55: =HistoricalFS!G81/HistoricalFS!G$92 -> 0 | H55: =HistoricalFS!H81/HistoricalFS!H$92 -> 0.00066664826
B56: =HistoricalFS!B83 -> CURRENT LIABILITIES
B57: =HistoricalFS!B84 -> Borrowings | C57: =HistoricalFS!C84/HistoricalFS!C$92 -> 0.03690934 | D57: =HistoricalFS!D84/HistoricalFS!D$92 -> 0.022030605 | E57: =HistoricalFS!E84/HistoricalFS!E$92 -> 0.046776787 | F57: =HistoricalFS!F84/HistoricalFS!F$92 -> 0.033985682 | G57: =HistoricalFS!G84/HistoricalFS!G$92 -> 0.011768647 | H57: =HistoricalFS!H84/HistoricalFS!H$92 -> 0.013036403
B58: =HistoricalFS!B85 -> Trade payables - To micro & small enterprises | C58: =HistoricalFS!C85/HistoricalFS!C$92 -> 0.019762813 | D58: =HistoricalFS!D85/HistoricalFS!D$92 -> 0.060739807 | E58: =HistoricalFS!E85/HistoricalFS!E$92 -> 0.036043096 | F58: =HistoricalFS!F85/HistoricalFS!F$92 -> 0.045303981 | G58: =HistoricalFS!G85/HistoricalFS!G$92 -> 0.059234221 | H58: =HistoricalFS!H85/HistoricalFS!H$92 -> 0.053840565
B59: =HistoricalFS!B86 -> Trade payables - To other than micro & small enterprises | C59: =HistoricalFS!C86/HistoricalFS!C$92 -> 0.17550563 | D59: =HistoricalFS!D86/HistoricalFS!D$92 -> 0.11525977 | E59: =HistoricalFS!E86/HistoricalFS!E$92 -> 0.095324059 | F59: =HistoricalFS!F86/HistoricalFS!F$92 -> 0.085300674 | G59: =HistoricalFS!G86/HistoricalFS!G$92 -> 0.076226813 | H59: =HistoricalFS!H86/HistoricalFS!H$92 -> 0.086295205
B60: =HistoricalFS!B87 -> Other current financial liabilities | C60: =HistoricalFS!C87/HistoricalFS!C$92 -> 0.11454264 | D60: =HistoricalFS!D87/HistoricalFS!D$92 -> 0.10199786 | E60: =HistoricalFS!E87/HistoricalFS!E$92 -> 0.085506129 | F60: =HistoricalFS!F87/HistoricalFS!F$92 -> 0.094700314 | G60: =HistoricalFS!G87/HistoricalFS!G$92 -> 0.088078521 | H60: =HistoricalFS!H87/HistoricalFS!H$92 -> 0.08097684
B61: =HistoricalFS!B88 -> Other current liabilities | C61: =HistoricalFS!C88/HistoricalFS!C$92 -> 0.12044911 | D61: =HistoricalFS!D88/HistoricalFS!D$92 -> 0.075557281 | E61: =HistoricalFS!E88/HistoricalFS!E$92 -> 0.062475917 | F61: =HistoricalFS!F88/HistoricalFS!F$92 -> 0.05323061 | G61: =HistoricalFS!G88/HistoricalFS!G$92 -> 0.058897695 | H61: =HistoricalFS!H88/HistoricalFS!H$92 -> 0.066102941
B62: =HistoricalFS!B89 -> Provisions | C62: =HistoricalFS!C89/HistoricalFS!C$92 -> 0.003413899 | D62: =HistoricalFS!D89/HistoricalFS!D$92 -> 0.0039301754 | E62: =HistoricalFS!E89/HistoricalFS!E$92 -> 0.0079153799 | F62: =HistoricalFS!F89/HistoricalFS!F$92 -> 0.0062696574 | G62: =HistoricalFS!G89/HistoricalFS!G$92 -> 0.0046757414 | H62: =HistoricalFS!H89/HistoricalFS!H$92 -> 0.003929999
B63: =HistoricalFS!B90 -> Current Tax Liabilities (net) | C63: =HistoricalFS!C90/HistoricalFS!C$92 -> 0.0031937709 | D63: =HistoricalFS!D90/HistoricalFS!D$92 -> 0.0012453853 | E63: =HistoricalFS!E90/HistoricalFS!E$92 -> 0 | F63: =HistoricalFS!F90/HistoricalFS!F$92 -> 0.0038530904 | G63: =HistoricalFS!G90/HistoricalFS!G$92 -> 0.001394913 | H63: =HistoricalFS!H90/HistoricalFS!H$92 -> 0.0054811041
B65: =HistoricalFS!B92 -> TOTAL EQUITY AND LIABILITIES | C65: =HistoricalFS!C92/HistoricalFS!C92 -> 1 | D65: =HistoricalFS!D92/HistoricalFS!D92 -> 1 | E65: =HistoricalFS!E92/HistoricalFS!E92 -> 1 | F65: =HistoricalFS!F92/HistoricalFS!F92 -> 1 | G65: =HistoricalFS!G92/HistoricalFS!G92 -> 1 | H65: =HistoricalFS!H92/HistoricalFS!H92 -> 1

Sheet Rm
B2: Hawkins Cookers Limited
B7: Return on Market
B9: Year | C9: Annual | G9: Median
B10: 2000 | C10: -0.1465 | E10: Average Return | F10: =AVERAGE(C10:C35) -> 0.15149231 | G10: =MEDIAN(C10:C35) -> 0.1135
B11: 2001 | C11: -0.1618 | E11: Dividend Yield | F11: 0.013 | G11: =F11 -> 0.013
B12: 2002 | C12: 0.0325
B13: 2003 | C13: 0.719 | E13: Total Market Return | F13: =SUM(F10:F11) -> 0.16449231 | G13: =SUM(G10:G11) -> 0.1265
B14: 2004 | C14: 0.1068
B15: 2005 | C15: 0.3634
B16: 2006 | C16: 0.3983
B17: 2007 | C17: 0.5477
B18: 2008 | C18: -0.5179
B19: 2009 | C19: 0.7576
B20: 2010 | C20: 0.1795
B21: 2011 | C21: -0.2462
B22: 2012 | C22: 0.277
B23: 2013 | C23: 0.0676
B24: 2014 | C24: 0.3139
B25: 2015 | C25: -0.0406
... B35: 2025 | C35: 0.1051
B36: 2026

Sheet Beta - Regression
B2: Hawkins Cookers Limited
P4: (Values in Rs. Lakhs)
B6: Regression Beta - 2 Years Weekly
B8: Hawkins Cookers Limited - Weekly Returns | F8: Nifty 50 - Weekly Returns | I8: Beta Drifting
B10: Date | C10: Closing Price | D10: Returns | F10: Adj Close | G10: Returns | I10: Levered Raw Beta | J10: =M13 -> 0.18276103 | L10: Beta 1 | M10: =SLOPE(D12:D115,G12:G115) -> 0.18588113
B11: 45516 | C11: 8329.1396 | F11: 24541.15 | I11: Beta Weight | J11: 0.75 | L11: Beta 2 | M11: =_xlfn.COVARIANCE.S(D11:D115,G11:G115)/_xlfn.VAR.S(G11:G115) -> 0.18588113
B12: 45523 | C12: 8430.875 | D12: =C12/C11-1 -> 0.012214389 | F12: 24823.15 | G12: =F12/F11-1 -> 0.011490904
B13: 45530 | C13: 8154.3027 | D13: =C13/C12-1 -> -0.032804693 | F13: 25235.9 | G13: =F13/F12-1 -> 0.016627624 | I13: Market Beta | J13: 1 | L13: Beta 3 | M13: =J40 -> 0.18276103
B14: 45537 | C14: 8318.3145 | D14: =C14/C13-1 -> 0.020113518 | F14: 24852.15 | G14: =F14/F13-1 -> -0.015206511 | I14: Market Beta Weight | J14: =1-J11 -> 0.25
B15: 45544 | C15: 8630.8057 | D15: =C15/C14-1 -> 0.03756665 | F15: 25356.5 | G15: =F15/F14-1 -> 0.020294003
B16: 45551 | C16: 8634.0566 | D16: =C16/C15-1 -> 0.00037667127 | F16: 25790.949 | G16: =F16/F15-1 -> 0.017133643 | I16: Adjusted Beta | J16: =(J10*J11)+(J13*J14) -> 0.38707077
B17: 45558 | C17: 8443.6416 | D17: =C17/C16-1 -> -0.022053948 | F17: 26178.949 | G17: =F17/F16-1 -> 0.015044037
B18: 45565 | C18: 8397.335 | D18: =C18/C17-1 -> -0.0054842025 | F18: 25014.6 | G18: =F18/F17-1 -> -0.04447656 | I18: SUMMARY OUTPUT
B19: 45572 | C19: 8540.0869 | D19: =C19/C18-1 -> 0.016999674 | F19: 24964.25 | G19: =F19/F18-1 -> -0.0020128089
B20: 45579 | C20: 8339.3311 | D20: =C20/C19-1 -> -0.023507473 | F20: 24854.051 | G20: =F20/F19-1 -> -0.0044142812 | I20: Regression Statistics
B21: 45586 | C21: 8203.376 | D21: =C21/C20-1 -> -0.016302876 | F21: 24180.801 | G21: =F21/F20-1 -> -0.02708814 | I21: Multiple R | J21: 0.11617301
B22: 45593 | C22: 8534.9893 | D22: =C22/C21-1 -> 0.040424001 | F22: 24304.35 | G22: =F22/F21-1 -> 0.005109377 | I22: R Square | J22: 0.013496168
B23: 45600 | C23: 8493.3428 | D23: =C23/C22-1 -> -0.0048795005 | F23: 24148.199 | G23: =F23/F22-1 -> -0.006424792 | I23: Adjusted R Square | J23: 0.003728803
B24: 45607 | C24: 8202.9873 | D24: =C24/C23-1 -> -0.034186242 | F24: 23532.699 | G24: =F24/F23-1 -> -0.025488443 | I24: Standard Error | J24: 0.0293215
B25: 45614 | C25: 8267.3008 | D25: =C25/C24-1 -> 0.0078402507 | F25: 23907.25 | G25: =F25/F24-1 -> 0.015916184 | I25: Observations | J25: 103
B26: 45621 | C26: 8263.5146 | D26: =C26/C25-1 -> -0.00045796481 | F26: 24131.1 | G26: =F26/F25-1 -> 0.0093632521
B27: 45628 | C27: 8184.9312 | D27: =C27/C26-1 -> -0.0095096941 | F27: 24677.801 | G27: =F27/F26-1 -> 0.02265546 | I27: ANOVA
B28: 45635 | C28: 8497.6152 | D28: =C28/C27-1 -> 0.038202408 | F28: 24768.301 | G28: =F28/F27-1 -> 0.0036672636 | J28: df | K28: SS
B29: 45642 | C29: 8690.3613 | D29: =C29/C28-1 -> 0.022682375 | F29: 23587.5 | G29: =F29/F28-1 -> -0.047673871 | I29: Regression | J29: 1 | K29: 0.0011879699
B30: 45649 | C30: 8797.0488 | D30: =C30/C29-1 -> 0.012276532 | F30: 23813.4 | G30: =F30/F29-1 -> 0.0095771231 | I30: Residual | J30: 101 | K30: 0.086834786
B31: 45656 | C31: 8774.9639 | D31: =C31/C30-1 -> -0.0025104966 | F31: 24004.75 | G31: =F31/F30-1 -> 0.0080353753 | I31: Total | J31: 102 | K31: 0.088022756
B32: 45663 | C32: 8667.79 | D32: =C32/C31-1 -> -0.012213592 | F32: 23431.5 | G32: =F32/F31-1 -> -0.02388069
B33: 45670 | C33: 8489.1211 | D33: =C33/C32-1 -> -0.020612976 | F33: 23203.199 | G33: =F33/F32-1 -> -0.0097433276 | I33: MS | J33: F | K33: Significance F
B34: 45677 | C34: 8351.0781 | D34: =C34/C33-1 -> -0.016261161 | F34: 23092.199 | G34: =F34/F33-1 -> -0.0047838231 | I34: 0.0011879699 | J34: 1.3817614 | K34: 0.24256491
B35: 45684 | C35: 8119.356 | D35: =C35/C34-1 -> -0.027747575 | F35: 23482.15 | G35: =F35/F34-1 -> 0.016886706 | I35: 0.00085975036
B36: 45691 | C36: 8347.9229 | D36: =C36/C35-1 -> 0.028150865 | F36: 23559.949 | G36: =F36/F35-1 -> 0.0033131049
B37: 45698 | C37: 7434.479 | D37: =C37/C36-1 -> -0.10942169 | F37: 22929.25 | G37: =F37/F36-1 -> -0.026769974
B38: 45705 | C38: 7326.9668 | D38: =C38/C37-1 -> -0.014461297 | F38: 22795.9 | G38: =F38/F37-1 -> -0.0058156987 | J38: Coefficients | K38: Standard Error
B39: 45712 | C39: 7278.5737 | D39: =C39/C38-1 -> -0.0066047886 | F39: 22124.699 | G39: =F39/F38-1 -> -0.029443942 | I39: Intercept | J39: 0.00033399701 | K39: 0.0028891335
B40: 45719 | C40: 7136.4536 | D40: =C40/C39-1 -> -0.01952582 | F40: 22552.5 | G40: =F40/F39-1 -> 0.019335891 | I40: 0.011490904 | J40: 0.18276103 | K40: 0.15547732
B41: 45726 | C41: 7148.103 | D41: =C41/C40-1 -> 0.0016323814 | F41: 22397.199 | G41: =F41/F40-1 -> -0.0068861892
B42: 45733 | C42: 7076.8486 | D42: =C42/C41-1 -> -0.0099682943 | F42: 23350.4 | G42: =F42/F41-1 -> 0.042558945 | I42: t Stat | J42: P-value | K42: Lower 95%
B43: 45740 | C43: 7003.4092 | D43: =C43/C42-1 -> -0.010377423 | F43: 23519.35 | G43: =F43/F42-1 -> 0.0072353885 | I43: 0.11560456 | J43: 0.90819548 | K43: -0.0053972667
B44: 45747 | C44: 7389.6294 | D44: =C44/C43-1 -> 0.055147458 | F44: 22904.449 | G44: =F44/F43-1 -> -0.026144447 | I44: 1.1754835 | J44: 0.24256491 | K44: -0.12566416
B45: 45754 | C45: 7426.2759 | D45: =C45/C44-1 -> 0.0049591776 | F45: 22828.551 | G45: =F45/F44-1 -> -0.0033136984
B46: 45761 | C46: 7741.5327 | D46: =C46/C45-1 -> 0.042451538 | F46: 23851.65 | G46: =F46/F45-1 -> 0.044816669 | I46: Upper 95% | J46: Lower 95.0% | K46: Upper 95.0%
B47: 45768 | C47: 7679.064 | D47: =C47/C46-1 -> -0.0080693 | F47: 24039.35 | G47: =F47/F46-1 -> 0.0078694437 | I47: 0.0060652607 | J47: -0.0053972667 | K47: 0.0060652607
B48: 45775 | C48: 7756.4341 | D48: =C48/C47-1 -> 0.010075462 | F48: 24346.699 | G48: =F48/F47-1 -> 0.012785271 | I48: 0.49118621 | J48: -0.12566416 | K48: 0.49118621
B49: 45782 | C49: 7746.7266 | D49: =C49/C48-1 -> -0.0012515441 | F49: 24008 | G49: =F49/F48-1 -> -0.013911505
B50: 45789 | C50: 7674.7925 | D50: =C50/C49-1 -> -0.0092857391 | F50: 25019.801 | G50: =F50/F49-1 -> 0.042144318
B51: 45796 | C51: 7728.3306 | D51: =C51/C50-1 -> 0.006975835 | F51: 24853.15 | G51: =F51/F50-1 -> -0.0066607401
B52: 45803 | C52: 7684.7432 | D52: =C52/C51-1 -> -0.0056399506 | F52: 24750.699 | G52: =F52/F51-1 -> -0.004122261
B53: 45810 | C53: 7601.4995 | D53: =C53/C52-1 -> -0.010832327 | F53: 25003.051 | G53: =F53/F52-1 -> 0.010195735
B54: 45817 | C54: 7636.8354 | D54: =C54/C53-1 -> 0.0046485483 | F54: 24718.6 | G54: =F54/F53-1 -> -0.011376659
B55: 45824 | C55: 7726.4863 | D55: =C55/C54-1 -> 0.011739271 | F55: 25112.4 | G55: =F55/F54-1 -> 0.015931355
B56: 45831 | C56: 7895.0596 | D56: =C56/C55-1 -> 0.021817581 | F56: 25637.801 | G56: =F56/F55-1 -> 0.02092195
B57: 45838 | C57: 8480.918 | D57: =C57/C56-1 -> 0.074205697 | F57: 25461 | G57: =F57/F56-1 -> -0.0068960978
B58: 45845 | C58: 9034.4014 | D58: =C58/C57-1 -> 0.065262204 | F58: 25149.85 | G58: =F58/F57-1 -> -0.012220667
B59: 45852 | C59: 9362.084 | D59: =C59/C58-1 -> 0.03627054 | F59: 24968.4 | G59: =F59/F58-1 -> -0.0072147238
B60: 45859 | C60: 9124.9736 | D60: =C60/C59-1 -> -0.025326664 | F60: 24837 | G60: =F60/F59-1 -> -0.0052626676
... B115: 46244 | C115: 8351.6504 | D115: =C115/C114-1 -> 0.0039731184 | F115: 24366 | G115: =F115/F114-1 -> -0.0083290587

Sheet Beta - Comps
B2: Hawkins Cookers Limited
B6: S.No. | C6: Name | D6: CMP Rs. | E6: Mar Cap Rs.Cr. | F6: Debt Rs.Cr. | G6: Debt / Eq
B7: 1 | C7: Cello World | D7: 377.6 | E7: 8340.62 | F7: 38.11 | G7: 0.01
B8: 2 | C8: Hawkins Cookers | D8: 8351 | E8: 4417.68 | F8: 29.39 | G8: 0.07
B9: 3 | C9: Borosil | D9: 238.55 | E9: 2852.76 | F9: 148.08 | G9: 0.17
B10: 4 | C10: All Time Plastic | D10: 215.54 | E10: 1411.95 | F10: 86.4 | G10: 0.14

Sheet Intrinsic Growth
B2: Hawkins Cookers Limited
B6: Calculation of ROIC | F6: 2021 | G6: 2022 | H6: 2023 | I6: 2024 | J6: 2025 | K6: 2026
B8: Current Operating Assets
B9: Inventories | F9: ='Balance Sheet'!B18 -> 9717.53 | G9: ='Balance Sheet'!C18 -> 17810.07 | H9: ='Balance Sheet'!D18 -> 16956.37 | I9: ='Balance Sheet'!E18 -> 14045.67 | J9: ='Balance Sheet'!F18 -> 15016.63 | K9: ='Balance Sheet'!G18 -> 19296.57
B10: Trade receivables | F10: ='Balance Sheet'!B20 -> 4000.29 | G10: ='Balance Sheet'!C20 -> 5282.95 | H10: ='Balance Sheet'!D20 -> 4741.56 | I10: ='Balance Sheet'!E20 -> 4770.81 | J10: ='Balance Sheet'!F20 -> 6099.88 | K10: ='Balance Sheet'!G20 -> 5760.91
B11: Other current assets | F11: ='Balance Sheet'!B24 -> 2306.33 | G11: ='Balance Sheet'!C24 -> 4618.89 | H11: ='Balance Sheet'!D24 -> 5669.81 | I11: ='Balance Sheet'!E24 -> 4548.34 | J11: ='Balance Sheet'!F24 -> 4959.61 | K11: ='Balance Sheet'!G24 -> 9322.46
B12: Total Current Operating Assets | F12: =SUM(F9:F11) -> 16024.15 | G12: =SUM(G9:G11) -> 27711.91 | H12: =SUM(H9:H11) -> 27367.74 | I12: =SUM(I9:I11) -> 23364.82 | J12: =SUM(J9:J11) -> 26076.12 | K12: =SUM(K9:K11) -> 34379.94
B14: Current Operating Liabilities
B15: Trade payables - To micro & small enterprises | F15: ='Balance Sheet'!B43 -> 774.79 | G15: ='Balance Sheet'!C43 -> 2488.83 | H15: ='Balance Sheet'!D43 -> 1659.36 | I15: ='Balance Sheet'!E43 -> 2383.9 | J15: ='Balance Sheet'!F43 -> 3458.73 | K15: ='Balance Sheet'!G43 -> 3705.41
B16: Trade payables - To other than micro & small enterprises | F16: ='Balance Sheet'!B44 -> 6880.6 | G16: ='Balance Sheet'!C44 -> 4722.8 | H16: ='Balance Sheet'!D44 -> 4388.55 | I16: ='Balance Sheet'!E44 -> 4488.53 | J16: ='Balance Sheet'!F44 -> 4450.94 | K16: ='Balance Sheet'!G44 -> 5939
B17: Other current liabilities | F17: ='Balance Sheet'!B46 -> 4722.14 | G17: ='Balance Sheet'!C46 -> 3095.98 | H17: ='Balance Sheet'!D46 -> 2876.28 | I17: ='Balance Sheet'!E46 -> 2801 | J17: ='Balance Sheet'!F46 -> 3439.08 | K17: ='Balance Sheet'!G46 -> 4549.33
B18: Total Current Operating Liabilities | F18: =SUM(F15:F17) -> 12377.53 | G18: =SUM(G15:G17) -> 10307.61 | H18: =SUM(H15:H17) -> 8924.19 | I18: =SUM(I15:I17) -> 9673.43 | J18: =SUM(J15:J17) -> 11348.75 | K18: =SUM(K15:K17) -> 14193.74
B20: Net Operating Working Capital | F20: =F12-F18 -> 3646.62 | G20: =G12-G18 -> 17404.3 | H20: =H12-H18 -> 18443.55 | I20: =I12-I18 -> 13691.39 | J20: =J12-J18 -> 14727.37 | K20: =K12-K18 -> 20186.2
B22: Non Current Assets
B23: Property, Plant and Equipment | F23: ='Balance Sheet'!B7 -> 3891.85 | G23: ='Balance Sheet'!C7 -> 5162.06 | H23: ='Balance Sheet'!D7 -> 6601.99 | I23: ='Balance Sheet'!E7 -> 7195.46 | J23: ='Balance Sheet'!F7 -> 8432.04 | K23: ='Balance Sheet'!G7 -> 11997.55
B24: Capital Work-in-Progress | F24: ='Balance Sheet'!B8 -> 277.98 | G24: ='Balance Sheet'!C8 -> 323.11 | H24: ='Balance Sheet'!D8 -> 215.95 | I24: ='Balance Sheet'!E8 -> 1188.22 | J24: ='Balance Sheet'!F8 -> 2245.13 | K24: ='Balance Sheet'!G8 -> 1194.98
B25: Intangible assets | F25: ='Balance Sheet'!B9 -> 9.49 | G25: ='Balance Sheet'!C9 -> 17.19 | H25: ='Balance Sheet'!D9 -> 15.28 | I25: ='Balance Sheet'!E9 -> 11.87 | J25: ='Balance Sheet'!F9 -> 45.98 | K25: ='Balance Sheet'!G9 -> 68.94
B26: Net Non Current Assets | F26: =SUM(F23:F25) -> 4179.32 | G26: =SUM(G23:G25) -> 5502.36 | H26: =SUM(H23:H25) -> 6833.22 | I26: =SUM(I23:I25) -> 8395.55 | J26: =SUM(J23:J25) -> 10723.15 | K26: =SUM(K23:K25) -> 13261.47
B28: Invested Capital | F28: =F26+F20 -> 7825.94 | G28: =G26+G20 -> 22906.66 | H28: =H26+H20 -> 25276.77 | I28: =I26+I20 -> 22086.94 | J28: =J26+J20 -> 25450.52 | K28: =K26+K20 -> 33447.67
B29: EBIT | F29: =HistoricalFS!C33+HistoricalFS!C24 -> 11279.76 | G29: =HistoricalFS!D33+HistoricalFS!D24 -> 11896.34 | H29: =HistoricalFS!E33+HistoricalFS!E24 -> 13177.41 | I29: =HistoricalFS!F33+HistoricalFS!F24 -> 15209.93 | J29: =HistoricalFS!G33+HistoricalFS!G24 -> 15777.61 | K29: =HistoricalFS!H33+HistoricalFS!H24 -> 18014.56
B30: Tax rate | F30: 0.25 | G30: 0.25 | H30: 0.25 | I30: 0.25 | J30: 0.25 | K30: 0.25
B31: NOPAT | F31: =F29*(1-F30) -> 8459.82 | G31: =G29*(1-G30) -> 8922.255 | H31: =H29*(1-H30) -> 9883.0575 | I31: =I29*(1-I30) -> 11407.448 | J31: =J29*(1-J30) -> 11833.207 | K31: =K29*(1-K30) -> 13510.92
B33: ROIC | F33: =F31/F28 -> 1.0809973 | G33: =G31/G28 -> 0.38950484 | H33: =H31/H28 -> 0.39099369 | I33: =I31/I28 -> 0.51647931 | J33: =J31/J28 -> 0.46494954 | K33: =K31/K28 -> 0.40394204
B36: Calculation of Reinvestment Rate | F36: 2021 | G36: 2022 | H36: 2023 | I36: 2024 | J36: 2025 | K36: 2026
B38: Net Capex | F38: =-SUM('Cash Flow'!B32:B33)-HistoricalFS!C27 -> 855.53 | G38: =-SUM('Cash Flow'!C32:C33)-HistoricalFS!D27 -> 1323.83 | H38: =-SUM('Cash Flow'!D32:D33)-HistoricalFS!E27 -> 1231.12 | I38: =-SUM('Cash Flow'!E32:E33)-HistoricalFS!F27 -> 1693.85 | J38: =-SUM('Cash Flow'!F32:F33)-HistoricalFS!G27 -> 2235.66 | K38: =-SUM('Cash Flow'!G32:G33)-HistoricalFS!H27 -> 2552
B39: Change in Working Capital | G39: =G20-F20 -> 13757.68 | H39: =H20-G20 -> 1039.25 | I39: =I20-H20 -> -4752.16 | J39: =J20-I20 -> 1035.98 | K39: =K20-J20 -> 5458.83
B40: NOPAT | F40: =F31 -> 8459.82 | G40: =G31 -> 8922.255 | H40: =H31 -> 9883.0575 | I40: =I31 -> 11407.448 | J40: =J31 -> 11833.207 | K40: =K31 -> 13510.92
B42: Reinvestment | G42: =SUM(G38:G39) -> 15081.51 | H42: =SUM(H38:H39) -> 2270.37 | I42: =SUM(I38:I39) -> -3058.31 | J42: =SUM(J38:J39) -> 3271.64 | K42: =SUM(K38:K39) -> 8010.83
B44: Reinvestment Rate | G44: =G42/G40 -> 1.6903249 | H44: =H42/H40 -> 0.22972344 | I44: =I42/I40 -> -0.26809766 | J44: =J42/J40 -> 0.27647956 | K44: =K42/K40 -> 0.59291521
I46: 5 Year Average | K46: =AVERAGE(G44:K44) -> 0.5042691
I47: 5 Year Median | K47: =MEDIAN(G44:K44) -> 0.27647956
B49: Calculation of Growth Rate | F49: 2021 | G49: 2022 | H49: 2023 | I49: 2024 | J49: 2025 | K49: 2026
B51: Reinvestment Rate | G51: =G44 -> 1.6903249 | H51: =H44 -> 0.22972344 | I51: =I44 -> -0.26809766 | J51: =J44 -> 0.27647956 | K51: =K44 -> 0.59291521
B52: ROIC | G52: =G33 -> 0.38950484 | H52: =H33 -> 0.39099369 | I52: =I33 -> 0.51647931 | J52: =J33 -> 0.46494954 | K52: =K33 -> 0.40394204
B54: Intrinsic Growth | G54: =G51*G52 -> 0.65838974 | H54: =H51*H52 -> 0.089820416 | I54: =I51*I52 -> -0.13846689 | J54: =J51*J52 -> 0.12854904 | K54: =K51*K52 -> 0.23950338
I56: 5 Year Average | K56: =AVERAGE(G54:K54) -> 0.19555914
I57: 5 Year Median | K57: =MEDIAN(G54:K54) -> 0.12854904

Sheet DCF (FCFF)
B2: Hawkins Cookers Limited
H5: (Values in Rs. Lakhs)
B6: Calculation of PV of FCFF | D6: 2026 | E6: =D6+1 -> 2027 | F6: =E6+1 -> 2028 | G6: =F6+1 -> 2029 | H6: =G6+1 -> 2030 | I6: =H6+1 -> 2031
B8: EBIT | D8: =HistoricalFS!H33+HistoricalFS!H24 -> 18014.56 | E8: =D8*(1+$C$18) -> 20330.314 | F8: =E8*(1+$C$18) -> 22943.757 | G8: =F8*(1+$C$18) -> 25893.155 | H8: =G8*(1+$C$18) -> 29221.695 | I8: =H8*(1+$C$18) -> 32978.116
B9: Tax Rate | D9: 0.25 | E9: 0.25 | F9: 0.25 | G9: 0.25 | H9: 0.25 | I9: 0.25
B10: NOPAT | D10: =D8*(1-D9) -> 13510.92 | E10: =E8*(1-E9) -> 15247.736 | F10: =F8*(1-F9) -> 17207.818 | G10: =G8*(1-G9) -> 19419.866 | H10: =H8*(1-H9) -> 21916.271 | I10: =I8*(1-I9) -> 24733.587
B11: less : Reinvestment Rate | D11: ='Intrinsic Growth'!K47 -> 0.27647956 | E11: =D11 -> 0.27647956 | F11: =E11 -> 0.27647956 | G11: =F11 -> 0.27647956 | H11: =G11 -> 0.27647956 | I11: =H11 -> 0.27647956
B12: Free Cash Flow to Firm (FCFF) | D12: =D10*(1-D11) -> 9775.4268 | E12: =E10*(1-E11) -> 11032.049 | F12: =F10*(1-F11) -> 12450.208 | G12: =G10*(1-G11) -> 14050.67 | H12: =H10*(1-H11) -> 15856.87 | I12: =I10*(1-I11) -> 17895.256
B13: Mid Year Convention | E13: 0.5 | F13: =E13+1 -> 1.5 | G13: =F13+1 -> 2.5 | H13: =G13+1 -> 3.5 | I13: =H13+1 -> 4.5
B14: Discounting Factor | E14: =1/(1+$C$20)^E13 -> 0.92140356 | F14: =1/(1+$C$20)^F13 -> 0.78225737 | G14: =1/(1+$C$20)^G13 -> 0.6641244 | H14: =1/(1+$C$20)^H13 -> 0.56383134 | I14: =1/(1+$C$20)^I13 -> 0.47868408
B16: PV of FCFF | E16: =E12*E14 -> 10164.969 | F16: =F12*F14 -> 9739.2668 | G16: =G12*G14 -> 9331.3928 | H16: =H12*H14 -> 8940.6004 | I16: =I12*I14 -> 8566.1741
B18: Expecred Growth | C18: ='Intrinsic Growth'!K57 -> 0.12854904
B19: Terminal Growth | C19: 0.065
B20: WACC | C20: =WACC!J48 -> 0.17787777
B22: Calculation of Terminal Value
B24: FCFF (n+1) | C24: =I12*(1+C18) -> 20195.674
B25: WACC | C25: =C20 -> 0.17787777
B26: Terminal Growth Rate | C26: =C19 -> 0.065
B28: Terminal Value | C28: =C24/(C25-C26) -> 178916.31
B30: Calculation of Equity Value Per Share
B32: PV of FCFF | C32: =SUM(E16:I16) -> 46742.403
B33: PV of Terminal Value | C33: =C28*I14 -> 85644.387
B34: Value of Operating Assets | C34: =SUM(C32:C33) -> 132386.79
B36: Add: Cash | C36: =SUM(HistoricalFS!H66:H67) -> 19092.11
B37: Less: Debt | C37: =SUM(HistoricalFS!H78,HistoricalFS!H84) -> 2938.81
B38: Value of Equity | C38: =C34+C36-C37 -> 148540.09
B39: No. of Equity Shares | C39: =HistoricalFS!H42 -> 52.87815
B41: Equity Value Per Share | C41: =C38/C39 -> 2809.1015
B42: Share Price | C42: 8030
B43: Discount/Premium | C43: =C42/C41 -> 2.8585653

Sheet Comps 
B2: Hawkins Cookers Limited
B6: Comparable Company Valuation | P6: (Values in Rs. Crores)
D8: Market Data | K8: Financials | O8: Valuation
B9: Company | C9: Ticker | D9: Share Price | E9: Shares Outstanding | F9: Equity Value | G9: Net Debt | H9: Enterprise Value | K9: Revenue | L9: EBITDA | M9: Net Income | O9: EV/Revenue | P9: EV/EBITDA | Q9: P/E
B11: ='Comps Val Datasheet'!C3 -> Cello World | C11: ='Comps Val Datasheet'!E13 -> CELLO | D11: ='Comps Val Datasheet'!D3 -> 354.5 | E11: ='Comps Val Datasheet'!E3 -> 22.09 | F11: =D11*E11 -> 7830.905 | G11: ='Comps Val Datasheet'!I3 -> -89.66 | H11: =F11+G11 -> 7741.245 | K11: ='Comps Val Datasheet'!J3 -> 2321.41 | L11: ='Comps Val Datasheet'!M3 -> 510.7102 | M11: ='Comps Val Datasheet'!K3 -> 331.51 | O11: =H11/K11 -> 3.3347168 | P11: =H11/L11 -> 15.157804 | Q11: =F11/M11 -> 23.621927
B12: ='Comps Val Datasheet'!C4 -> Hawkins Cookers | C12: ='Comps Val Datasheet'!E14 -> HAWKINCOOK | D12: ='Comps Val Datasheet'!D4 -> 8152.5 | E12: ='Comps Val Datasheet'!E4 -> 0.53 | F12: =D12*E12 -> 4320.825 | G12: ='Comps Val Datasheet'!I4 -> -161.53 | H12: =F12+G12 -> 4159.295 | K12: ='Comps Val Datasheet'!J4 -> 1331.98 | L12: ='Comps Val Datasheet'!M4 -> 199.797 | M12: ='Comps Val Datasheet'!K4 -> 131.19 | O12: =H12/K12 -> 3.1226407 | P12: =H12/L12 -> 20.817605 | Q12: =F12/M12 -> 32.935628
B13: ='Comps Val Datasheet'!C5 -> Borosil | C13: ='Comps Val Datasheet'!E15 -> BOROLTD | D13: ='Comps Val Datasheet'!D5 -> 261.45 | E13: ='Comps Val Datasheet'!E5 -> 11.96 | F13: =D13*E13 -> 3126.942 | G13: ='Comps Val Datasheet'!I5 -> 144.88 | H13: =F13+G13 -> 3271.822 | K13: ='Comps Val Datasheet'!J5 -> 1216.82 | L13: ='Comps Val Datasheet'!M5 -> 194.6912 | M13: ='Comps Val Datasheet'!K5 -> 74.66 | O13: =H13/K13 -> 2.6888299 | P13: =H13/L13 -> 16.805187 | Q13: =F13/M13 -> 41.882427
B14: ='Comps Val Datasheet'!C6 -> All Time Plastic | C14: ='Comps Val Datasheet'!E16 -> ALLTIME | D14: ='Comps Val Datasheet'!D6 -> 204.62 | E14: ='Comps Val Datasheet'!E6 -> 6.55 | F14: =D14*E14 -> 1340.261 | G14: ='Comps Val Datasheet'!I6 -> -13.93 | H14: =F14+G14 -> 1326.331 | K14: ='Comps Val Datasheet'!J6 -> 613.5 | L14: ='Comps Val Datasheet'!M6 -> 92.025 | M14: ='Comps Val Datasheet'!K6 -> 35.6 | O14: =H14/K14 -> 2.1619087 | P14: =H14/L14 -> 14.412725 | Q14: =F14/M14 -> 37.647781
B15: ='Comps Val Datasheet'!C7 -> Clay Craft India | C15: ='Comps Val Datasheet'!E17 -> CLAYCRAFT | D15: ='Comps Val Datasheet'!D7 -> 159.15 | E15: ='Comps Val Datasheet'!E7 -> 2.06 | F15: =D15*E15 -> 327.849 | G15: ='Comps Val Datasheet'!I7 -> 16.75 | H15: =F15+G15 -> 344.599 | K15: ='Comps Val Datasheet'!J7 -> 178.75 | L15: ='Comps Val Datasheet'!M7 -> 46.475 | M15: ='Comps Val Datasheet'!K7 -> 26.91 | O15: =H15/K15 -> 1.9278266 | P15: =H15/L15 -> 7.4147176 | Q15: =F15/M15 -> 12.183166
B16: ='Comps Val Datasheet'!C8 -> Maruti Interior | C16: ='Comps Val Datasheet'!E18 -> SPITZE | D16: ='Comps Val Datasheet'!D8 -> 31.44 | E16: ='Comps Val Datasheet'!E8 -> 6.04 | F16: =D16*E16 -> 189.8976 | G16: ='Comps Val Datasheet'!I8 -> 25.15 | H16: =F16+G16 -> 215.0476 | K16: ='Comps Val Datasheet'!J8 -> 52.68 | L16: ='Comps Val Datasheet'!M8 -> 13.6968 | M16: ='Comps Val Datasheet'!K8 -> 10.44 | O16: =H16/K16 -> 4.0821488 | P16: =H16/L16 -> 15.700572 | Q16: =F16/M16 -> 18.189425
B17: ='Comps Val Datasheet'!C9 -> Inflame Applian. | C17: ='Comps Val Datasheet'!E19 -> INFLAME | D17: ='Comps Val Datasheet'!D9 -> 244.05 | E17: ='Comps Val Datasheet'!E9 -> 0.75 | F17: =D17*E17 -> 183.0375 | G17: ='Comps Val Datasheet'!I9 -> 48.4 | H17: =F17+G17 -> 231.4375 | K17: ='Comps Val Datasheet'!J9 -> 151.25 | L17: ='Comps Val Datasheet'!M9 -> 19.6625 | M17: ='Comps Val Datasheet'!K9 -> 5.8 | O17: =H17/K17 -> 1.5301653 | P17: =H17/L17 -> 11.770502 | Q17: =F17/M17 -> 31.55819
B19: High | O19: =MAX(O11:O17) -> 4.0821488 | P19: =MAX(P11:P17) -> 20.817605 | Q19: =MAX(Q11:Q17) -> 41.882427
B20: 75th Percentile | O20: =QUARTILE(O11:O17,3) -> 3.2286788 | P20: =QUARTILE(P11:P17,3) -> 16.25288 | Q20: =QUARTILE(Q11:Q17,3) -> 35.291704
B21: Average | O21: =AVERAGE(O11:O17) -> 2.6926053 | P21: =AVERAGE(P11:P17) -> 14.58273 | Q21: =AVERAGE(Q11:Q17) -> 28.288363
B22: Median | O22: =MEDIAN(O11:O17) -> 2.6888299 | P22: =MEDIAN(P11:P17) -> 15.157804 | Q22: =MEDIAN(Q11:Q17) -> 31.55819
B23: 25th Percentile | O23: =QUARTILE(O13:O19,1) -> 1.9863471 | P23: =QUARTILE(P13:P19,1) -> 12.431058 | Q23: =QUARTILE(Q13:Q19,1) -> 21.531616
B24: Low | O24: =MIN(O11:O17) -> 1.5301653 | P24: =MIN(P11:P17) -> 7.4147176 | Q24: =MIN(Q11:Q17) -> 12.183166
B26: Hawkins Cookers Limited Comparable Valuation | O26: EV/Revenue | P26: EV/EBITDA | Q26: P/E
B28: Implied Enterprise Value | O28: =O22*K12 -> 3581.4677 | P28: =P22*L12 -> 3028.4837 | Q28: =Q30+Q29 -> 3978.5889
B29: Net Debt | O29: =G12 -> -161.53 | P29: =O29 -> -161.53 | Q29: =P29 -> -161.53
B30: Implied Market Value | O30: =O28-O29 -> 3742.9977 | P30: =P28-P29 -> 3190.0137 | Q30: =Q22*M12 -> 4140.1189
B31: Shares Outstanding | O31: =E12 -> 0.53 | P31: =O31 -> 0.53 | Q31: =P31 -> 0.53
B33: Implied Value Per Share | O33: =O30/O31 -> 7062.2597 | P33: =P30/P31 -> 6018.8938 | Q33: =Q30/Q31 -> 7811.5451
O34: =IF(O33<$D$12,"Overvalued","Undervalued") -> Overvalued | P34: =IF(P33<$D$12,"Overvalued","Undervalued") -> Overvalued | Q34: =IF(Q33<$D$12,"Overvalued","Undervalued") -> Overvalued

Sheet Comps Val Datasheet
B2: S.No. | C2: Name | D2: CMP Rs. | E2: No. Eq. Shares Cr. | F2: Equity Value | G2: Debt Rs.Cr. | H2: Cash End Rs.Cr. | I2: Net Debt | J2: Sales Rs.Cr. | K2: NP Ann Rs.Cr. | L2: EBITDA Margin | M2: EBITDA
B3: 1 | C3: Cello World | D3: 354.5 | E3: 22.09 | G3: 38.11 | H3: 127.77 | I3: =G3-(H3) -> -89.66 | J3: 2321.41 | K3: 331.51 | L3: 0.22 | M3: =J3*L3 -> 510.7102
B4: 2 | C4: Hawkins Cookers | D4: 8152.5 | E4: 0.53 | G4: 29.39 | H4: 190.92 | I4: =G4-(H4) -> -161.53 | J4: 1331.98 | K4: 131.19 | L4: 0.15 | M4: =J4*L4 -> 199.797
B5: 3 | C5: Borosil | D5: 261.45 | E5: 11.96 | G5: 148.08 | H5: 3.2 | I5: =G5-(H5) -> 144.88 | J5: 1216.82 | K5: 74.66 | L5: 0.16 | M5: =J5*L5 -> 194.6912
B6: 4 | C6: All Time Plastic | D6: 204.62 | E6: 6.55 | G6: 86.4 | H6: 100.33 | I6: =G6-(H6) -> -13.93 | J6: 613.5 | K6: 35.6 | L6: 0.15 | M6: =J6*L6 -> 92.025
B7: 5 | C7: Clay Craft India | D7: 159.15 | E7: 2.06 | G7: 49.98 | H7: 33.23 | I7: =G7-(H7) -> 16.75 | J7: 178.75 | K7: 26.91 | L7: 0.26 | M7: =J7*L7 -> 46.475
B8: 6 | C8: Maruti Interior | D8: 31.44 | E8: 6.04 | G8: 26.53 | H8: 1.38 | I8: =G8-(H8) -> 25.15 | J8: 52.68 | K8: 10.44 | L8: 0.26 | M8: =J8*L8 -> 13.6968
B9: 7 | C9: Inflame Applian. | D9: 244.05 | E9: 0.75 | G9: 52.54 | H9: 4.14 | I9: =G9-(H9) -> 48.4 | J9: 151.25 | K9: 5.8 | L9: 0.13 | M9: =J9*L9 -> 19.6625
E13: CELLO
E14: HAWKINCOOK
E15: BOROLTD
E16: ALLTIME
E17: CLAYCRAFT
E18: SPITZE
E19: INFLAME

Sheet Income Statement
A1: Hawkins Cookers Limited — Historical Income Statement
A2: Source: Hawkins Annual Reports 2021-22, 2023-24 and 2025-26 | Rs. Lakhs | Historical reported figures | G2: Values in Lakhs
A3: Particulars | B3: FY2021 | C3: FY2022 | D3: FY2023 | E3: FY2024 | F3: FY2025 | G3: FY2026
A4: Income
A5: Revenue from operations (net) | B5: 76845.94 | C5: 95801.19 | D5: 100579.5 | E5: 102414.97 | F5: 111575.66 | G5: 125292.73
A6: Other Income | B6: 731.98 | C6: 586.12 | D6: 416 | E6: 1058.36 | F6: 1352.86 | G6: 1297.9
A7: Total Income | B7: 77577.91 | C7: 96387.31 | D7: 100995.5 | E7: 103473.34 | F7: 112928.52 | G7: 126590.63
A8: Expenses:
A9: Cost of materials consumed | B9: 24611.08 | C9: 39317.95 | D9: 40464.48 | E9: 35362.55 | F9: 42387.9 | G9: 48651.54
A10: Purchases of Stock-in-Trade | B10: 8385.2 | C10: 15003.36 | D10: 10521.48 | E10: 12118.3 | F10: 11814.15 | G10: 14386.23
A11: Changes in inventories of Finished Goods, Work-in-Progress and Stock-in-Trade | B11: 3523.43 | C11: -5439 | D11: 153.84 | E11: 1818.7 | F11: -531.96 | G11: -1383.77
A12: Employee benefits expense | B12: 10094.85 | C12: 10618.57 | D12: 11273.53 | E12: 11569.31 | F12: 12249.8 | G12: 12862.72
A13: Finance costs | B13: 473.48 | C13: 605.71 | D13: 486.31 | E13: 455.02 | F13: 290.31 | G13: 352.88
A14: Depreciation and amortization expense | B14: 533.14 | C14: 665.71 | D14: 771.96 | E14: 868.39 | F14: 1029.16 | G14: 1359.61
A15: Other expenses | B15: 19150.46 | C15: 24324.38 | D15: 24632.8 | E15: 26526.15 | F15: 30201.86 | G15: 32699.74
A16: Total Expenses | B16: 66771.65 | C16: 85096.68 | D16: 88304.41 | E16: 88718.41 | F16: 97441.22 | G16: 108928.95
A17: Profit before tax | B17: 10806.26 | C17: 11290.64 | D17: 12691.09 | E17: 14754.92 | F17: 15487.3 | G17: 17661.68
A18: Tax expense: | B18: 2742.71 | C18: 2902.01 | D18: 3213.38 | E18: 3771.33 | F18: 4018.03 | G18: 4542.85
A19: Current tax | B19: 2685 | C19: 2827 | D19: 3287.53 | E19: 3759 | F19: 3899.13 | G19: 4463
A20: Deferred tax | B20: 57.71 | C20: 75.01 | D20: -74.15 | E20: 12.33 | F20: 118.9 | G20: 79.85
A21: Profit for the year (A) | B21: 8063.55 | C21: 8388.63 | D21: 9477.71 | E21: 10983.6 | F21: 11469.27 | G21: 13118.83
A22: Other Comprehensive Income
A23: Items that will not be reclassified to Profit or Loss
A24: Actuarial Loss/(Gain) on Defined Benefit Plans | B24: -48.53 | C24: -99.58 | D24: -13.32 | E24: 52.39 | F24: -197 | G24: -59.56
A25: Tax Effect on the above | B25: 12.21 | C25: 25.52 | D25: 3.35 | E25: -13.19 | F25: 49.58 | G25: 14.99
A26: Items that will be reclassified to Profit or Loss | B26: 0 | C26: 0 | D26: 0 | E26: 0 | F26: 0 | G26: 0
A27: Total Other Comprehensive Income for the year (B) | B27: -36.31 | C27: -74.06 | D27: -9.97 | E27: 39.2 | F27: -147.42 | G27: -44.57
A28: Total Comprehensive Income for the year (A+B) | B28: 8027.23 | C28: 8314.57 | D28: 9467.75 | E28: 11022.8 | F28: 11321.85 | G28: 13074.25
A29: Earnings Per Share
A30: Basic and Diluted (Rs.) | B30: 152.49 | C30: 158.64 | D30: 179.24 | E30: 207.72 | F30: 216.9 | G30: 248.1

Sheet Balance Sheet
A1: Hawkins Cookers Limited — Historical Balance Sheet
A2: Source: Hawkins Annual Reports 2021-22, 2023-24 and 2025-26 | Rs. Lakhs | Historical reported figures
A4: Particulars | B4: FY2021 | C4: FY2022 | D4: FY2023 | E4: FY2024 | F4: FY2025 | G4: FY2026
A5: ASSETS
A6: NON-CURRENT ASSETS
A7: Property, Plant and Equipment | B7: 3891.85 | C7: 5162.06 | D7: 6601.99 | E7: 7195.46 | F7: 8432.04 | G7: 11997.55
A8: Capital Work-in-Progress | B8: 277.98 | C8: 323.11 | D8: 215.95 | E8: 1188.22 | F8: 2245.13 | G8: 1194.98
A9: Intangible assets | B9: 9.49 | C9: 17.19 | D9: 15.28 | E9: 11.87 | F9: 45.98 | G9: 68.94
A10: Financial Assets
A11: Investments | B11: 0.25 | C11: 0.25 | D11: 0.25 | E11: 0.25 | F11: 0.25 | G11: 0.25
A12: Other non-current financial assets | B12: 1109.62 | C12: 130.47 | D12: 779.34 | E12: 445.84 | F12: 936.04 | G12: 543.14
A13: Non-current tax assets (net) | B13: 208.62 | C13: 316.71 | D13: 296.08 | E13: 315.17 | F13: 443.25 | G13: 421.74
A14: Deferred tax assets (net) | B14: 85.79 | C14: 36.3 | D14: 113.8 | E14: 88.29 | F14: 18.97 | G14: 0
A15: Other non-current assets | B15: 364.97 | C15: 521.32 | D15: 556.08 | E15: 684.15 | F15: 625.93 | G15: 668.89
A16: Total Non-current Assets | B16: 5948.57 | C16: 6507.4 | D16: 8578.77 | E16: 9929.26 | F16: 12747.59 | G16: 14895.48
A17: CURRENT ASSETS
A18: Inventories | B18: 9717.53 | C18: 17810.07 | D18: 16956.37 | E18: 14045.67 | F18: 15016.63 | G18: 19296.57
A19: Financial Assets
A20: Trade receivables | B20: 4000.29 | C20: 5282.95 | D20: 4741.56 | E20: 4770.81 | F20: 6099.88 | G20: 5760.91
A21: Cash and cash equivalents | B21: 2133.57 | C21: 315.42 | D21: 1144.31 | E21: 1206.21 | F21: 1074.26 | G21: 1569.45
A22: Bank balances other than above | B22: 14574.68 | C22: 6198.47 | D22: 8710.34 | E22: 17628.87 | F22: 17900.06 | G22: 17522.66
A23: Other current financial assets | B23: 523.47 | C23: 242.07 | D23: 237.07 | E23: 490.93 | F23: 592.71 | G23: 454.39
A24: Other current assets | B24: 2306.33 | C24: 4618.89 | D24: 5669.81 | E24: 4548.34 | F24: 4959.61 | G24: 9322.46
A25: Total Current Assets | B25: 33255.87 | C25: 34467.87 | D25: 37459.45 | E25: 42690.84 | F25: 45643.14 | G25: 53926.44
A26: TOTAL ASSETS | B26: 39204.44 | C26: 40975.27 | D26: 46038.22 | E26: 52620.1 | F26: 58390.73 | G26: 68821.92
A27: EQUITY AND LIABILITIES
A28: EQUITY
A29: Equity Share Capital | B29: 528.78 | C29: 528.78 | D29: 528.78 | E29: 528.78 | F29: 528.78 | G29: 528.78
A30: Other Equity | B30: 17233.66 | C30: 20789.2 | D30: 27084.25 | E30: 32819.24 | F30: 37795.72 | G30: 43995.81
A31: Total Equity | B31: 17762.44 | C31: 21317.98 | D31: 27613.04 | E31: 33348.02 | F31: 38324.5 | G31: 44524.59
A32: LIABILITIES
A33: NON-CURRENT LIABILITIES
A34: Financial Liabilities
A35: Borrowings | B35: 2305.76 | C35: 3437.12 | D35: 2077.63 | E35: 1347.56 | F35: 1625.45 | G35: 2041.62
A36: Other non-current financial liabilities | B36: 0 | C36: 0 | D36: 124.97 | E36: 51.27 | F36: 76.56 | G36: 105.26
A37: Provisions | B37: 562.07 | C37: 618.39 | D37: 843.92 | E37: 895.69 | F37: 830.86 | G37: 792.95
A38: Deferred tax liabilities (net) | B38: 0 | C38: 0 | D38: 0 | E38: 0 | F38: 0 | G38: 45.88
A39: Total Non-current Liabilities | B39: 2867.83 | C39: 4055.51 | D39: 3046.52 | E39: 2294.52 | F39: 2532.87 | G39: 2985.72
A40: CURRENT LIABILITIES
A41: Financial Liabilities
A42: Borrowings | B42: 1447.01 | C42: 902.71 | D42: 2153.52 | E42: 1788.33 | F42: 687.18 | G42: 897.19
A43: Trade payables - To micro & small enterprises | B43: 774.79 | C43: 2488.83 | D43: 1659.36 | E43: 2383.9 | F43: 3458.73 | G43: 3705.41
A44: Trade payables - To other than micro & small enterprises | B44: 6880.6 | C44: 4722.8 | D44: 4388.55 | E44: 4488.53 | F44: 4450.94 | G44: 5939
A45: Other current financial liabilities | B45: 4490.58 | C45: 4179.39 | D45: 3936.55 | E45: 4983.14 | F45: 5142.97 | G45: 5572.98
A46: Other current liabilities | B46: 4722.14 | C46: 3095.98 | D46: 2876.28 | E46: 2801 | F46: 3439.08 | G46: 4549.33
A47: Provisions | B47: 133.84 | C47: 161.04 | D47: 364.41 | E47: 329.91 | F47: 273.02 | G47: 270.47
A48: Current Tax Liabilities (net) | B48: 125.21 | C48: 51.03 | D48: 0 | E48: 202.75 | F48: 81.45 | G48: 377.22
A49: Total Current Liabilities | B49: 18574.16 | C49: 15601.78 | D49: 15378.67 | E49: 16977.56 | F49: 17533.36 | G49: 21311.6
A50: TOTAL EQUITY AND LIABILITIES | B50: 39204.44 | C50: 40975.27 | D50: 46038.22 | E50: 52620.1 | F50: 58390.73 | G50: 68821.92

Sheet Cash Flow
A1: Hawkins Cookers Limited — Historical Cash Flow Statement
A2: Source: Hawkins Annual Reports 2021-22, 2023-24 and 2025-26 | Rs. Lakhs | Historical reported figures
A4: Particulars | B4: FY2021 | C4: FY2022 | D4: FY2023 | E4: FY2024 | F4: FY2025 | G4: FY2026
A5: A. Cash Flow from Operating Activities
A6: Profit before tax | B6: 10806.26 | C6: 11290.64 | D6: 12691.09 | E6: 14754.92 | F6: 15487.3 | G6: 17661.68
A7: Adjustments for:
A8: Depreciation and amortization expense | B8: 533.14 | C8: 665.71 | D8: 771.96 | E8: 868.39 | F8: 1029.16 | G8: 1359.61
A9: Profit/(Loss) on sale of property, plant and equipment (net) | B9: -12.63 | C9: -10.69 | D9: -1.08 | E9: 4.05 | F9: -0.51 | G9: -2.37
A10: Interest income | B10: -650.75 | C10: -564.6 | D10: -406.89 | E10: -1047 | F10: -1322.95 | G10: -1296.42
A11: Dividend income | B11: 0 | C11: -0.05 | D11: -0.05 | E11: -0.04 | F11: -0.04 | G11: -0.04
A12: Finance costs | B12: 473.48 | C12: 605.71 | D12: 486.31 | E12: 455.02 | F12: 290.31 | G12: 352.88
A13: Operating profit before working capital changes | B13: 11149.5 | C13: 11986.71 | D13: 13541.34 | E13: 15035.34 | F13: 15483.27 | G13: 18075.34
A14: Changes in working capital
A15: Adjustments for — increase/decrease in operating assets
A16: Inventories | B16: 3583.74 | C16: -8092.53 | D16: 853.7 | E16: 2910.69 | F16: -970.96 | G16: -4279.94
A17: Trade receivables | B17: 1021.02 | C17: -1282.67 | D17: 541.39 | E17: -29.25 | F17: -1329.07 | G17: 338.96
A18: Other current financial assets | B18: -36.34 | C18: 30.02 | D18: 46.86 | E18: 14.89 | F18: -19.07 | G18: 17.1
A19: Other current assets | B19: -6.67 | C19: -2312.56 | D19: -1050.93 | E19: 1121.47 | F19: -411.27 | G19: -4362.85
A20: Other non-current financial assets | B20: -7.55 | C20: -15.85 | D20: -51.87 | E20: -13.5 | F20: -40.2 | G20: -8.1
A21: Other non-current assets | B21: 37.76 | C21: -144.87 | D21: -133.42 | E21: -0.6 | F21: -33.2 | G21: -26.9
A22: Adjustments for increase/decrease in operating liabilities
A23: Trade payables | B23: 2724.53 | C23: -443.75 | D23: -1036.98 | E23: 824.53 | F23: 1037.24 | G23: 1734.73
A24: Non-current provision | B24: 164.43 | C24: 56.32 | D24: 225.53 | E24: 51.77 | F24: -64.83 | G24: -97.47
A25: Current provision | B25: -33.5 | C25: 27.2 | D25: 203.37 | E25: -34.5 | F25: -56.89 | G25: -2.55
A26: Other current financial liabilities | B26: 662.2 | C26: -387.76 | D26: -374.86 | E26: 1195.77 | F26: 106.65 | G26: 406.47
A27: Other current liabilities | B27: 2246.97 | C27: -1626.16 | D27: -219.7 | E27: -75.28 | F27: 638.08 | G27: 1110.25
A28: Cash generated from operations | B28: 21506.09 | C28: -2205.88 | D28: 12544.43 | E28: 21001.32 | F28: 14339.76 | G28: 12905.06
A29: Income taxes paid (net) | B29: -2612.18 | C29: -3009.27 | D29: -3317.93 | E29: -3575.34 | F29: -4148.51 | G29: -4145.72
A30: Net Cash from/—used in Operating Activities | B30: 18893.91 | C30: -5215.15 | D30: 9226.51 | E30: 17425.99 | F30: 10191.25 | G30: 8759.34
A31: B. Cash Flow from Investing Activities
A32: Purchase of property, plant and equipment (including capital advances and CWIP) | B32: -1406.69 | C32: -2011.25 | D32: -2014.55 | E32: -2564.88 | F32: -3273.87 | G32: -3937.88
A33: Sale of property, plant and equipment | B33: 18.02 | C33: 21.71 | D33: 11.47 | E33: 2.64 | F33: 9.05 | G33: 26.27
A34: Decrease/—Increase in fixed deposits with banks | B34: -10917.58 | C34: 9371.2 | D34: -3108.86 | E34: -8571.54 | F34: -721.18 | G34: 788.54
A35: Interest received | B35: 367.37 | C35: 815.99 | D35: 365.02 | E35: 778.25 | F35: 1240.25 | G35: 1417.63
A36: Dividend received | B36: 0 | C36: 0.05 | D36: 0.05 | E36: 0.04 | F36: 0.04 | G36: 0.04
A37: Net Cash from/—used in Investing Activities | B37: -11938.89 | C37: 8197.7 | D37: -4746.87 | E37: -10355.49 | F37: -2745.71 | G37: -1705.39
A38: C. Cash Flow from Financing Activities
A39: Finance costs paid | B39: -563.76 | C39: -610.18 | D39: -333.47 | E39: -589.3 | F39: -396.92 | G39: -310.78
A40: Dividend paid | B40: -4242.05 | C40: -4777.57 | D40: -3208.6 | E40: -5324.03 | F40: -6357.3 | G40: -6874.16
A41: Proceeds from fixed deposits | B41: 1289.05 | C41: 1068.83 | D41: 525.84 | E41: 484.31 | F41: 415.75 | G41: 850.91
A42: Repayment of fixed deposits | B42: -499.02 | C42: -809.04 | D42: -308.57 | E42: -1578.25 | F42: -1239.01 | G42: -224.73
A43: Net Cash used in Financing Activities | B43: -4015.77 | C43: -5127.96 | D43: -3324.81 | E43: -7007.27 | F43: -7577.48 | G43: -6558.76
A44: Net Increase/—Decrease in Cash and Cash Equivalents A+B+C | B44: 2939.25 | C44: -2145.41 | D44: 1154.83 | E44: 63.22 | F44: -131.95 | G44: 495.19
A45: Cash and cash equivalents at the commencement of the year | B45: -805.68 | C45: 2133.57 | D45: -11.84 | E45: 1142.99 | F45: 1206.21 | G45: 1074.26
A46: Cash and cash equivalents as at the end of the year | B46: 2133.57 | C46: -11.84 | D46: 1142.99 | E46: 1206.21 | F46: 1074.26 | G46: 1569.45
A47: Net Increase/—Decrease in Cash and Cash Equivalents E-D | B47: 2939.25 | C47: -2145.41 | D47: 1154.83 | E47: 63.22 | F47: -131.95 | G47: 495.19

Sheet Checks
A1: Hawkins Cookers Limited — Historical Financial Statement Checks
A2: Formula-driven integrity checks | Historical data in Rs. Lakhs
A4: Check | C4: FY2021 | D4: FY2022 | E4: FY2023 | F4: FY2024 | G4: FY2025 | H4: FY2026
A5: Balance Sheet: Total Assets - Total Equity & Liabilities | B5: check | C5: ='Balance Sheet'!B26='Balance Sheet'!B50 -> TRUE | D5: ='Balance Sheet'!C26='Balance Sheet'!C50 -> TRUE | E5: ='Balance Sheet'!D26='Balance Sheet'!D50 -> TRUE | F5: ='Balance Sheet'!E26='Balance Sheet'!E50 -> TRUE | G5: ='Balance Sheet'!F26='Balance Sheet'!F50 -> TRUE | H5: ='Balance Sheet'!G26='Balance Sheet'!G50 -> TRUE
A6: Income Statement: Total Income - Total Expenses - Profit Before Tax | B6: check | C6: ='Income Statement'!B7-'Income Statement'!B16-'Income Statement'!B17 -> 0 | D6: ='Income Statement'!C7-'Income Statement'!C16-'Income Statement'!C17 -> -0.01 | E6: ='Income Statement'!D7-'Income Statement'!D16-'Income Statement'!D17 -> 0 | F6: ='Income Statement'!E7-'Income Statement'!E16-'Income Statement'!E17 -> 0.01 | G6: ='Income Statement'!F7-'Income Statement'!F16-'Income Statement'!F17 -> 0 | H6: ='Income Statement'!G7-'Income Statement'!G16-'Income Statement'!G17 -> 0
A7: Income Statement: PBT - Tax Expense - Profit for the Year | B7: check | C7: ='Income Statement'!B17-'Income Statement'!B18-'Income Statement'!B21 -> 0 | D7: ='Income Statement'!C17-'Income Statement'!C18-'Income Statement'!C21 -> 0 | E7: ='Income Statement'!D17-'Income Statement'!D18-'Income Statement'!D21 -> 0 | F7: ='Income Statement'!E17-'Income Statement'!E18-'Income Statement'!E21 -> -0.01 | G7: ='Income Statement'!F17-'Income Statement'!F18-'Income Statement'!F21 -> 0 | H7: ='Income Statement'!G17-'Income Statement'!G18-'Income Statement'!G21 -> 0
A8: Cash Flow: CFO + CFI + CFF - Net Change | B8: check | C8: ='Cash Flow'!B30+'Cash Flow'!B37+'Cash Flow'!B43-'Cash Flow'!B44 -> 0 | D8: ='Cash Flow'!C30+'Cash Flow'!C37+'Cash Flow'!C43-'Cash Flow'!C44 -> 0 | E8: ='Cash Flow'!D30+'Cash Flow'!D37+'Cash Flow'!D43-'Cash Flow'!D44 -> 0 | F8: ='Cash Flow'!E30+'Cash Flow'!E37+'Cash Flow'!E43-'Cash Flow'!E44 -> 0.01 | G8: ='Cash Flow'!F30+'Cash Flow'!F37+'Cash Flow'!F43-'Cash Flow'!F44 -> 0.01 | H8: ='Cash Flow'!G30+'Cash Flow'!G37+'Cash Flow'!G43-'Cash Flow'!G44 -> 0
A9: Cash Flow: Opening Cash + Net Change - Closing Cash | B9: check | C9: ='Cash Flow'!B45+'Cash Flow'!B44-'Cash Flow'!B46 -> 0 | D9: ='Cash Flow'!C45+'Cash Flow'!C44-'Cash Flow'!C46 -> 3.0908609e-13 | E9: ='Cash Flow'!D45+'Cash Flow'!D44-'Cash Flow'!D46 -> 0 | F9: ='Cash Flow'!E45+'Cash Flow'!E44-'Cash Flow'!E46 -> 0 | G9: ='Cash Flow'!F45+'Cash Flow'!F44-'Cash Flow'!F46 -> 0 | H9: ='Cash Flow'!G45+'Cash Flow'!G44-'Cash Flow'!G46 -> 0
